Lab05/part3/alu.v
// CO224 - Lab05 PART-1
// GROUP - 11

// ALU module 
// 8-bit ALU unit, that can operate with two 8-bit numbers to generate the result
// give the relevant output to RESULT respect to SELECT 

// Input:
//      DATA1, DATA2, SELECT
// Output:
//      RESULT

// Operations:
//      FORWARD - forward the data in DATA2 into RESULT 
//      ADD     - add DATA1 and DATA2, give the addiction to RESULT
//      AND     - and DATA1 and DATA2, give the result to RESULT     
//      OR      - or DATA1 and DATA2, give the result to RESULT  

// SELECTION CODE:
//      FOEWARD - 000   
//      ADD     - 001
//      AND     - 010   
//      OR      - 011

module alu(DATA1, DATA2, RESULT, SELECT);

    // initailize input ports
    input [7:0] DATA1, DATA2;
    input [0:2] SELECT;
    // initailize output ports
    output [7:0] RESULT;

    // make wires for connect each module's outputs to the mux
    wire [7:0] forward_result, add_result, and_result, or_result;

    // make instances of for each module
    // FORWARD - alu_forward
    // ADD     - alu_add
    // AND     - alu_and
    // OR      - alu_or
    // connect each module's relevant input and output
    ALU_FORWARD alu_forward(DATA2, forward_result);
    ALU_ADD alu_add(DATA1, DATA2, add_result);
    ALU_AND alu_and(DATA1, DATA2, and_result);
    ALU_OR alu_or(DATA1, DATA2, or_result);

    // instantiation of the mux
    // connect all the the module's output to the mux 
    // select a input as the selection
    MUX mux(forward_result, add_result, and_result, or_result, RESULT, SELECT);

endmodule


// FORWARD module
// used to foward the 8 bit DATA2 directly to output of the module
// Inputs  - DATA2
// Outputs - RESULT
module ALU_FORWARD(DATA2, RESULT);

    // initailize input ports
    input [7:0] DATA2;
    // initailize output ports
    output [7:0] RESULT;

    // assigen the DATA2 value to RESULT with a 1 time unit delay
    assign #1 RESULT = DATA2;

endmodule


// ADD module
// 8 bit adder for add two 8 bit number and give a 8 bit result
// Inputs - DATA1, DATA2
// Output - RESULT
module ALU_ADD(DATA1, DATA2, RESULT);

    // initailize input ports
    input [7:0] DATA1, DATA2;
    // initailize output ports
    output [7:0] RESULT;

    // get the addition of DATA1 and DATA2 
    // assign the value to RESULT with a 2 time units delay
    assign #2 RESULT = DATA1 + DATA2;

endmodule


// AND module
// bitwise AND the give two 8 bit numbers and output a 8 bit number
// Inout  - DATA1, DATA2
// Output - RESULT
module ALU_AND(DATA1, DATA2, RESULT);

    // initailize input ports
    input [7:0] DATA1, DATA2;
    // initailize output ports
    output [7:0] RESULT;

    // AND bitwise each bit
    // assign it to RESULT with a 1 time unit delay
    assign #1 RESULT = DATA1 & DATA2;

endmodule


// OR module
// bitwise OR the give two 8 bit numbers and output a 8 bit number
// Inout  - DATA1, DATA2
// Output - RESULT
module ALU_OR(DATA1, DATA2, RESULT);

    // initailize input ports
    input [7:0] DATA1, DATA2;
    // initailize output ports
    output [7:0] RESULT;

    // and bitwise each bit
    // assign it to RESULT with a 1 time unit delay
    assign #1 RESULT = DATA1 | DATA2;

endmodule


// MUX module
// select a inputs for the inputs
// map it to the ouput reference to the selection bits
// Inputs  - forward_result, add_result, and_result, or_result, SELECT
// Outputs - RESULT
module MUX(forward_result, add_result, and_result, or_result, RESULT, SELECT);

    // initailize input ports
    input [7:0] forward_result, add_result, and_result, or_result;
    input [2:0] SELECT;
    // initailize output ports
    output [7:0] RESULT;
    // initailize the registers
    reg [7:0] RESULT;

    // set a always block to trigger when changing 
    // forward_result, add_result, and_result, or_result, SELECT
    // thus, if these inputs are change the output is change reference to selection bits
    always @(forward_result, add_result, and_result, or_result, SELECT) begin
        
        // case block to check the select bit
        // give the result value 
        case(SELECT)

            // selection for FORWARD
            3'b000 : RESULT = forward_result;
            // selection for ADD
            3'b001 : RESULT = add_result;
            // selection for AND
            3'b010 : RESULT = and_result;
            // selection for OR
            3'b011 : RESULT = or_result;

            // deafult routing
            default : RESULT = 0;
        endcase

    end

endmodule

Lab05/part3/modules.v
module two_comp(DATA, OUT);

    input [7:0] DATA;
    output [7:0] OUT;

    assign #1 OUT = ~DATA + 1;

endmodule


module mux(DATA1, DATA2, SELECT, OUTPUT);

    input [7:0] DATA1, DATA2;
    input SELECT;
    output reg [7:0] OUTPUT;

    always @(SELECT) begin 

        if (SELECT) 
            OUTPUT = DATA2;
        else
            OUTPUT = DATA1;

    end

endmodule

Lab05/part3/mycpu/reg_file.v
// CO224 - Lab05 PART-1
// GROUP - 11

// REGISTER FILE module
// 8x8 register file that can store 8-bit binary numbers
// register numbers are 0-7
// INPUT ports: 
//     INADDRESS, OUT1ADDRESS, OUT2ADDRESS : 3-bit
//     IN : 8-bit
//     WRITE, CLK, RESET : 1-bit
// OUTPUT ports:
//     OUT1, OUT2 : 8-bit
// Reading  - for given register numbers(OUT1ADDRESS, OUT2ADDRESS), 
//            OUT1 and OUT2 will output the stored value asynchronously
//            reading delay - 2 time unit
// Writting - to a given register numbers(INADDRESS),
//            IN data will write synchronously when a positive clk edge and WRITE is enable
//            writting delay - 1 time unit
// Reset    - when reset is enable, all the register values will reset to 0 in a positive clk edge
module reg_file(IN, OUT1, OUT2, INADDRESS, OUT1ADDRESS, OUT2ADDRESS, WRITE, CLK, RESET);

    // declare input ports
    input [7:0] IN; // data in
    input [2:0]  INADDRESS, OUT1ADDRESS, OUT2ADDRESS;   // register numbers 
    input  WRITE, CLK, RESET;   // control signals

    // declare output ports
    output [7:0] OUT1, OUT2;    // data out
    
    // declare the 8-bit, 8 registers
    reg [7:0] registers [7:0];

    // assign block for change the OUT1, in a change of OUT1ADDRESS or register values
    // with a 2 time unit delay
    assign #2 OUT1 = registers[OUT1ADDRESS];

    // assign block for chnage the OUT1, in a change of OUT2ADDRESS or register values
    // with a 2 time unit delay
    assign #2 OUT2 = registers[OUT2ADDRESS];

    // always block for check for a positive clk edge
    // to write a reg or reset registers
    always @(posedge CLK) begin
        
        // to write a register
        // WRITE should be enable and RESET should be desable
        if (WRITE && ~RESET) begin
            
            // select the appropriate reg numbers
            // writting takes 1 time unit time
            #1 registers[INADDRESS] = IN;

        end

        // if RESET is enable
        // set all the register values to 0
        if (RESET) begin        
            
            #1 // one time unit delay for resetting
            // loop through all the registers
            for (integer i=0; i<8; i=i+1) begin
                registers[i] = 0;   // assign 0 to the registers
            end

        end

    end

    always @(IN, OUT1, OUT2, INADDRESS, OUT1ADDRESS, OUT2ADDRESS, WRITE, CLK, RESET, registers[0], registers[1], registers[2], registers[3], registers[4], registers[5], registers[6], registers[7])
    $display($time, " %d %d %d %d %d %d %d %d %d %d %d %d %d %d %d %d %d",IN, OUT1, OUT2, INADDRESS, OUT1ADDRESS, OUT2ADDRESS, WRITE, CLK, RESET, registers[0], registers[1], registers[2], registers[3], registers[4], registers[5], registers[6], registers[7]);

endmodule

Lab05/part3/control_unit.v
module control_unit(OPCODE, WRITEENABLE, COMP_SELECT, IMMEDIATE_SELECT, ALUOP);

    input [7:0] OPCODE;
    output reg WRITEENABLE, COMP_SELECT, IMMEDIATE_SELECT;
    output reg [2:0] ALUOP;

    always @(OPCODE) begin 

        #1

        case (OPCODE)
            8'b0000_0000: begin
                WRITEENABLE = 1'b1;
                COMP_SELECT = 1'b0;
                IMMEDIATE_SELECT = 1'b1;
                ALUOP = 3'b000;
            end

            8'b0000_0001: begin
                WRITEENABLE = 1'b1;
                COMP_SELECT = 1'b0;
                IMMEDIATE_SELECT = 1'b0;
                ALUOP = 3'b000;
            end

            8'b0000_0010: begin
                WRITEENABLE = 1'b1;
                COMP_SELECT = 1'b0;
                IMMEDIATE_SELECT = 1'b0;
                ALUOP = 3'b001;
            end

            8'b0000_0011: begin
                WRITEENABLE = 1'b1;
                COMP_SELECT = 1'b1;
                IMMEDIATE_SELECT = 1'b0;
                ALUOP = 3'b001;
            end

            8'b0000_0100: begin
                WRITEENABLE = 1'b1;
                COMP_SELECT = 1'b0;
                IMMEDIATE_SELECT = 1'b0;
                ALUOP = 3'b010;
            end

            8'b0000_0101: begin
                WRITEENABLE = 1'b1;
                COMP_SELECT = 1'b0;
                IMMEDIATE_SELECT = 1'b0;
                ALUOP = 3'b011;
            end

        endcase

    end

endmodule

Lab05/part3/pc.v
module pc(RESET, CLK, PC);

    input RESET, CLK;
    output reg [31:0] PC;
    
    reg [31:0] PC_NEXT;
    wire [31:0] adder_out;

    pc_add pc_adder(PC, adder_out);

    initial
    PC = 0;

    always @(adder_out)
    PC_NEXT = adder_out;

    always @(posedge CLK) begin
        #1 PC = PC_NEXT;
    end 

endmodule

module pc_add(PC, adder_out);

    input [31:0] PC;
    output [31:0] adder_out;

    assign #1 adder_out = PC + 1;

endmodule

Lab05/part3/cpu.v
`include "alu.v"
`include "reg_file.v"
`include "pc.v"
`include "control_unit.v"
`include "modules.v"


module cpu(PC, INSTRUCTION, CLK, RESET);

    input CLK, RESET;
    input [31:0] INSTRUCTION;

    output [31:0] PC;

    wire [2:0] ALUOP;
    wire WRITEENABLE, COMPSELECT, IMMEDIATESELECT;
    wire [7:0] ALURESULT, REGOUT2, REGOUT1, COMPOUT, MUX1, ALUIN;


    pc Pc(RESET, CLK, PC);
    control_unit Control_Unit(INSTRUCTION[31:24], WRITEENABLE, COMPSELECT, IMMEDIATESELECT, ALUOP);
    reg_file Reg_File(ALURESULT, REGOUT1, REGOUT2, INSTRUCTION[18:16], INSTRUCTION[10:8], INSTRUCTION[2:0], WRITEENABLE, CLK,RESET);
    two_comp Two_Comp(REGOUT2, COMPOUT);

    mux Mux1(REGOUT2, COMPOUT, COMPSELECT, MUX1);
    mux Mux2(MUX1, INSTRUCTION[7:0], IMMEDIATESELECT, ALUIN);

    alu Alu(REGOUT1, ALUIN, ALURESULT, ALUOP);
    

endmodule

Lab05/part3/cpu_tb.v
`include "cpu.v"

module cpu_tb;

    reg RESET, CLK;
    wire [31:0] INSTRUCTION;
    wire [31:0] PC;

    cpu CPU(PC, INSTRUCTION, CLK, RESET);

    reg [31:0] instr_mem [255:0];

    assign #2 INSTRUCTION = instr_mem[PC];

    initial begin
        CLK = 0;
        RESET = 0;
        $monitor($time, " %b %b %b %b", PC, INSTRUCTION, CLK, RESET);

        $dumpfile("cpu_tb.vcd");
		$dumpvars(0, cpu_tb);

        #40 $finish;
    end

    initial begin
        // instr_mem[0] = 0;

        instr_mem[0] = 32'b00000001_00000001_00000011_00000010;
        instr_mem[1] = 32'b00000000_00000010_00000000_00000011;
        instr_mem[2] = 32'b00000000_00000001_00000000_00000010;
    end

    always
    #4 CLK = ~CLK;


endmodule

Lab05/part3/cpu_tb.vcd
$date
	Fri May 12 00:52:50 2023
$end
$version
	Icarus Verilog
$end
$timescale
	1s
$end
$scope module cpu_tb $end
$var wire 32 ! INSTRUCTION [31:0] $end
$var wire 32 " PC [31:0] $end
$var reg 1 # CLK $end
$var reg 1 $ RESET $end
$scope module CPU $end
$var wire 1 # CLK $end
$var wire 32 % INSTRUCTION [31:0] $end
$var wire 1 $ RESET $end
$var wire 1 & WRITEENABLE $end
$var wire 8 ' REGOUT2 [7:0] $end
$var wire 8 ( REGOUT1 [7:0] $end
$var wire 32 ) PC [31:0] $end
$var wire 8 * MUX1 [7:0] $end
$var wire 1 + IMMEDIATESELECT $end
$var wire 1 , COMPSELECT $end
$var wire 8 - COMPOUT [7:0] $end
$var wire 8 . ALURESULT [7:0] $end
$var wire 3 / ALUOP [2:0] $end
$var wire 8 0 ALUIN [7:0] $end
$scope module Alu $end
$var wire 8 1 or_result [7:0] $end
$var wire 8 2 forward_result [7:0] $end
$var wire 8 3 and_result [7:0] $end
$var wire 8 4 add_result [7:0] $end
$var wire 3 5 SELECT [0:2] $end
$var wire 8 6 RESULT [7:0] $end
$var wire 8 7 DATA2 [7:0] $end
$var wire 8 8 DATA1 [7:0] $end
$scope module alu_add $end
$var wire 8 9 RESULT [7:0] $end
$var wire 8 : DATA2 [7:0] $end
$var wire 8 ; DATA1 [7:0] $end
$upscope $end
$scope module alu_and $end
$var wire 8 < RESULT [7:0] $end
$var wire 8 = DATA2 [7:0] $end
$var wire 8 > DATA1 [7:0] $end
$upscope $end
$scope module alu_forward $end
$var wire 8 ? RESULT [7:0] $end
$var wire 8 @ DATA2 [7:0] $end
$upscope $end
$scope module alu_or $end
$var wire 8 A RESULT [7:0] $end
$var wire 8 B DATA2 [7:0] $end
$var wire 8 C DATA1 [7:0] $end
$upscope $end
$scope module mux $end
$var wire 8 D add_result [7:0] $end
$var wire 8 E and_result [7:0] $end
$var wire 8 F forward_result [7:0] $end
$var wire 8 G or_result [7:0] $end
$var wire 3 H SELECT [2:0] $end
$var reg 8 I RESULT [7:0] $end
$upscope $end
$upscope $end
$scope module Control_Unit $end
$var wire 8 J OPCODE [7:0] $end
$var reg 3 K ALUOP [2:0] $end
$var reg 1 , COMP_SELECT $end
$var reg 1 + IMMEDIATE_SELECT $end
$var reg 1 & WRITEENABLE $end
$upscope $end
$scope module Mux1 $end
$var wire 1 , SELECT $end
$var wire 8 L DATA2 [7:0] $end
$var wire 8 M DATA1 [7:0] $end
$var reg 8 N OUTPUT [7:0] $end
$upscope $end
$scope module Mux2 $end
$var wire 8 O DATA1 [7:0] $end
$var wire 8 P DATA2 [7:0] $end
$var wire 1 + SELECT $end
$var reg 8 Q OUTPUT [7:0] $end
$upscope $end
$scope module Pc $end
$var wire 1 # CLK $end
$var wire 1 $ RESET $end
$var wire 32 R adder_out [31:0] $end
$var reg 32 S PC [31:0] $end
$var reg 32 T PC_NEXT [31:0] $end
$scope module pc_adder $end
$var wire 32 U PC [31:0] $end
$var wire 32 V adder_out [31:0] $end
$upscope $end
$upscope $end
$scope module Reg_File $end
$var wire 1 # CLK $end
$var wire 8 W IN [7:0] $end
$var wire 3 X INADDRESS [2:0] $end
$var wire 8 Y OUT1 [7:0] $end
$var wire 3 Z OUT1ADDRESS [2:0] $end
$var wire 8 [ OUT2 [7:0] $end
$var wire 3 \ OUT2ADDRESS [2:0] $end
$var wire 1 $ RESET $end
$var wire 1 & WRITE $end
$scope begin $ivl_for_loop0 $end
$var integer 32 ] i [31:0] $end
$upscope $end
$upscope $end
$scope module Two_Comp $end
$var wire 8 ^ DATA [7:0] $end
$var wire 8 _ OUT [7:0] $end
$upscope $end
$upscope $end
$upscope $end
$enddefinitions $end
$comment Show the parameter values. $end
$dumpall
$end
#0
$dumpvars
bx _
bx ^
bx ]
bx \
bx [
bx Z
bx Y
bx X
bx W
bx V
bx U
bx T
bx S
bx R
bx Q
bx P
bx O
bx N
bx M
bx L
bx K
bx J
bx I
bx H
bx G
bx F
bx E
bx D
bx C
bx B
bx A
bx @
bx ?
bx >
bx =
bx <
bx ;
bx :
bx 9
bx 8
bx 7
bx 6
bx 5
bx 4
bx 3
bx 2
bx 1
bx 0
bx /
bx .
bx -
x,
x+
bx *
bx )
bx (
bx '
x&
bx %
0$
0#
bx "
bx !
$end
#1
b0 "
b0 )
b0 S
b0 U
#2
b100 T
b100 R
b100 V
#3
b1 J
b1 X
b11 Z
b10 \
b10 P
b1000000010000001100000010 !
b1000000010000001100000010 %
#4
b0 /
b0 5
b0 H
b0 K
0+
0,
1&
1#
#5
b100 "
b100 )
b100 S
b100 U
#6
b1000 T
b1000 R
b1000 V
#7
bx J
bx X
bx Z
bx \
bx P
bx !
bx %
#8
0#
#12
1#
#13
b1000 "
b1000 )
b1000 S
b1000 U
#14
b1100 T
b1100 R
b1100 V
#16
0#
#20
1#
#21
b1100 "
b1100 )
b1100 S
b1100 U
#22
b10000 T
b10000 R
b10000 V
#24
0#
#28
1#
#29
b10000 "
b10000 )
b10000 S
b10000 U
#30
b10100 T
b10100 R
b10100 V
#32
0#
#36
1#
#37
b10100 "
b10100 )
b10100 S
b10100 U
#38
b11000 T
b11000 R
b11000 V
