Lab05/part3/test/test.v

module cpu(PC, INSTRUCTION, CLK, RESET);

    input CLK, RESET;
    input [31:0] INSTRUCTION;

    output [31:0] PC;

    pc p(RESET, CLK, PC);

endmodule

// module control_unit;



// endmodule

module pc(RESET, CLK, PC);

    input RESET, CLK;
    output reg [31:0] PC;
    
    reg [31:0] PC_NEXT;
    wire [31:0] adder_out;

    pc_add pc_adder(PC, adder_out);

    initial
    PC = 0;

    always @(adder_out)
    PC_NEXT = adder_out;

    always @(posedge CLK) begin
        #1 PC = PC_NEXT;
    end 

endmodule

module pc_add(PC, adder_out);

    input [31:0] PC;
    output [31:0] adder_out;

    assign #1 adder_out = PC + 1;

endmodule

Lab05/part3/test/test_tb.v

`include "test.v"

module test_tb;

    reg RESET, CLK;
    reg [31:0] INSTRUCTION;
    wire [31:0] PC;

    reg [7:0] DATA;
    wire [7:0] OUT;


    cpu CPU(PC, INSTRUCTION, CLK, RESET);


    mux m(8'd1, 8'd2, 1'd0, OUT);

    always
    #5 CLK = ~CLK;

    initial
    #30 $finish;

    initial begin
        CLK = 0;
        $monitor($time, " %b %b %b %b %b %b", CLK, PC, INSTRUCTION, RESET, DATA, OUT);

        $dumpfile("test.vcd");
		$dumpvars(0, test_tb);

        #8 DATA = 2;

    end



endmodule

module two_comp(DATA, OUT);

    input [7:0] DATA;
    output [7:0] OUT;

    assign OUT = ~DATA + 1;

endmodule

module mux(DATA1, DATA2, SELECT, OUTPUT);

    input [7:0] DATA1, DATA2;
    input SELECT;
    output reg [7:0] OUTPUT;

    always @(SELECT) begin 

        if (SELECT) 
            OUTPUT = DATA1;
        else
            OUTPUT = DATA2;

    end

endmodule

Lab05/part3/test/test.vcd
$date
	Thu May 11 14:28:39 2023
$end
$version
	Icarus Verilog
$end
$timescale
	1s
$end
$scope module test_tb $end
$var wire 32 ! PC [31:0] $end
$var wire 8 " OUT [7:0] $end
$var reg 1 # CLK $end
$var reg 8 $ DATA [7:0] $end
$var reg 32 % INSTRUCTION [31:0] $end
$var reg 1 & RESET $end
$scope module CPU $end
$var wire 1 # CLK $end
$var wire 32 ' INSTRUCTION [31:0] $end
$var wire 1 & RESET $end
$var wire 32 ( PC [31:0] $end
$scope module p $end
$var wire 1 # CLK $end
$var wire 1 & RESET $end
$var wire 32 ) adder_out [31:0] $end
$var reg 32 * PC [31:0] $end
$var reg 32 + PC_NEXT [31:0] $end
$scope module pc_adder $end
$var wire 32 , PC [31:0] $end
$var wire 32 - adder_out [31:0] $end
$upscope $end
$upscope $end
$upscope $end
$scope module m $end
$var wire 8 . DATA1 [7:0] $end
$var wire 8 / DATA2 [7:0] $end
$var wire 1 0 SELECT $end
$var reg 8 1 OUTPUT [7:0] $end
$upscope $end
$upscope $end
$enddefinitions $end
$comment Show the parameter values. $end
$dumpall
$end
#0
$dumpvars
b10 1
00
b10 /
b1 .
bx -
b0 ,
bx +
b0 *
bx )
b0 (
bx '
x&
bx %
bx $
0#
b10 "
b0 !
$end
#1
b1 +
b1 )
b1 -
#5
1#
#6
b1 !
b1 (
b1 *
b1 ,
#7
b10 +
b10 )
b10 -
#8
b10 $
#10
0#
#15
1#
#16
b10 !
b10 (
b10 *
b10 ,
#17
b11 +
b11 )
b11 -
#20
0#
#25
1#
#26
b11 !
b11 (
b11 *
b11 ,
#27
b100 +
b100 )
b100 -
