Lab05/part1/alu.v

// ALU module 
// get two inputs as DATA1 and DATA2 
// give the relevant output to RESULT respect to SELECT 
module alu(DATA1, DATA2, RESULT, SELECT);

    // initailize input ports
    input [7:0] DATA1, DATA2;
    input [0:2] SELECT;
    // initailize output ports
    output [7:0] RESULT;

    // make wires for connect each module's outputs to the mux
    wire [7:0] forward_result, add_result, and_result, or_result;

    // make instances of for each module
    // FORWARD - alu_forward
    // ADD     - alu_add
    // AND     - alu_and
    // OR      - alu_or
    // connect each module's relevant input and output
    ALU_FORWARD alu_forward(DATA2, forward_result);
    ALU_ADD alu_add(DATA1, DATA2, add_result);
    ALU_AND alu_and(DATA1, DATA2, and_result);
    ALU_OR alu_or(DATA1, DATA2, or_result);

    // instantiation of the mux
    // connect all the the module's output to the mux 
    // select a input as the selection
    MUX mux(forward_result, add_result, and_result, or_result, RESULT, SELECT);

endmodule


// FORWARD module
// used to foward the 8 bit DATA2 directly to output of the module
// Inputs - DATA2
// Outputs - RESULT
module ALU_FORWARD(DATA2, RESULT);

    // initailize input ports
    input [7:0] DATA2;
    // initailize output ports
    output [7:0] RESULT;

    // assigen the DATA2 value to RESULT with a 1 time unit delay
    assign #1 RESULT = DATA2;

endmodule


// ADD module
// 8 bit adder for add two 8 bit number and give a 8 bit result
// Inputs - DATA1, DATA2
// Output - RESULT
module ALU_ADD(DATA1, DATA2, RESULT);

    // initailize input ports
    input [7:0] DATA1, DATA2;
    // initailize output ports
    output [7:0] RESULT;

    // get the addition of DATA1 and DATA2 
    // assign the value to RESULT with a 2 time units delay
    assign #2 RESULT = DATA1 + DATA2;

endmodule


// AND module
// bitwise AND the give two 8 bit numbers and output a 8 bit number
// Inout - DATA1, DATA2
// Output - RESULT
module ALU_AND(DATA1, DATA2, RESULT);

    // initailize input ports
    input [7:0] DATA1, DATA2;
    // initailize output ports
    output [7:0] RESULT;

    // AND bitwise each bit
    // assign it to RESULT with a 1 time unit delay
    assign #1 RESULT = DATA1 & DATA2;

endmodule


// OR module
// bitwise OR the give two 8 bit numbers and output a 8 bit number
// Inout - DATA1, DATA2
// Output - RESULT
module ALU_OR(DATA1, DATA2, RESULT);

    // initailize input ports
    input [7:0] DATA1, DATA2;
    // initailize output ports
    output [7:0] RESULT;

    // and bitwise each bit
    // assign it to RESULT with a 1 time unit delay
    assign #1 RESULT = DATA1 | DATA2;

endmodule


// MUX module
// select a inputs for the inputs
// map it to the ouput reference to the selection bits
// Inputs - forward_result, add_result, and_result, or_result, SELECT
// Outputs -RESULT
module MUX(forward_result, add_result, and_result, or_result, RESULT, SELECT);

    // initailize input ports
    input [7:0] forward_result, add_result, and_result, or_result;
    input [2:0] SELECT;
    // initailize output ports
    output [7:0] RESULT;
    // initailize the registers
    reg [7:0] RESULT;

    // set a always block to trigger when changing 
    // forward_result, add_result, and_result, or_result, SELECT
    // thus, if these inputs are change the output is change reference to selection bits
    always @(forward_result, add_result, and_result, or_result, SELECT) begin
        
        // case block to check the select bit
        // give the result value 
        case(SELECT)

            // selection for FORWARD
            3'b000 : RESULT = forward_result;
            // selection for ADD
            3'b001 : RESULT = add_result;
            // selection for AND
            3'b010 : RESULT = and_result;
            // selection for OR
            3'b011 : RESULT = or_result;

            // deafult routing
            default : RESULT = 0;
        endcase

    end

endmodule

Lab05/part1/alu_tb.v
// CO224 - Lab05 PART-1
// GROUP - 11
// Test bench for test ALU module

// include the alu module
`include "alu.v"

// test bench module for alu
module alu_tb;

    // declate the registers
    reg [7:0] DATA1, DATA2;
    reg [2:0] SELECT;
    // declare the wires
    wire [7:0] RESULT;

    // make the instance of the alu module
    alu ALU(DATA1, DATA2, RESULT, SELECT);

    // set the monitor to abserve the values
    initial begin
        $monitor($time, " SELECT = %b | DATA1 = %b, DATA2 = %b and RESULT = %b",SELECT, DATA1, DATA2, RESULT);

        // generate files needed to plot the waveform using GTKWave
        $dumpfile("alu_tb_waveform.vcd");
		$dumpvars(0, alu_tb);
    end

    // change the values and check the outputs
    initial begin
        // initiale values
        SELECT = 3'b000; 
        DATA1 = 8'b0000_0000; 
        DATA2 = 8'b0000_0000;

        // FORWARD functionality
        #5
        SELECT = 3'b000; 
        DATA1 = 8'b0000_0010; 
        DATA2 = 8'b0000_0001;
        
        // ADD funcationality
        #5
        SELECT = 3'b001; 
        DATA1 = 8'b0000_0001; 
        DATA2 = 8'b0000_0001;

        // AND funcationality
        #5
        SELECT = 3'b010; 
        DATA1 = 8'b0000_1111; 
        DATA2 = 8'b0000_0011;
        
        // OR funcationality
        #5
        SELECT = 3'b011; 
        DATA1 = 8'b0000_1001; 
        DATA2 = 8'b0000_1100;

        // change the selection only
        #5
        SELECT = 3'b001; 

        // change DATA1 only
        #5 
        DATA1 = 8'b0010_1000; 

        // change DATA2 only
        #5
        DATA2 = 8'b0000_0011;

        // AND funcationality
        #5
        SELECT = 3'b010; 
        DATA1 = 8'b0000_1001; 
        DATA2 = 8'b0000_1100;

    end

endmodule

Lab05/part1/alu_tb_waveform.vcd
$date
	Wed May 10 10:36:32 2023
$end
$version
	Icarus Verilog
$end
$timescale
	1s
$end
$scope module alu_tb $end
$var wire 8 ! RESULT [7:0] $end
$var reg 8 " DATA1 [7:0] $end
$var reg 8 # DATA2 [7:0] $end
$var reg 3 $ SELECT [2:0] $end
$scope module ALU $end
$var wire 8 % DATA1 [7:0] $end
$var wire 8 & DATA2 [7:0] $end
$var wire 3 ' SELECT [0:2] $end
$var wire 8 ( or_result [7:0] $end
$var wire 8 ) forward_result [7:0] $end
$var wire 8 * and_result [7:0] $end
$var wire 8 + add_result [7:0] $end
$var wire 8 , RESULT [7:0] $end
$scope module alu_add $end
$var wire 8 - DATA1 [7:0] $end
$var wire 8 . DATA2 [7:0] $end
$var wire 8 / RESULT [7:0] $end
$upscope $end
$scope module alu_and $end
$var wire 8 0 DATA1 [7:0] $end
$var wire 8 1 DATA2 [7:0] $end
$var wire 8 2 RESULT [7:0] $end
$upscope $end
$scope module alu_forward $end
$var wire 8 3 DATA2 [7:0] $end
$var wire 8 4 RESULT [7:0] $end
$upscope $end
$scope module alu_or $end
$var wire 8 5 DATA1 [7:0] $end
$var wire 8 6 DATA2 [7:0] $end
$var wire 8 7 RESULT [7:0] $end
$upscope $end
$scope module mux $end
$var wire 3 8 SELECT [2:0] $end
$var wire 8 9 add_result [7:0] $end
$var wire 8 : and_result [7:0] $end
$var wire 8 ; forward_result [7:0] $end
$var wire 8 < or_result [7:0] $end
$var reg 8 = RESULT [7:0] $end
$upscope $end
$upscope $end
$upscope $end
$enddefinitions $end
$comment Show the parameter values. $end
$dumpall
$end
#0
$dumpvars
bx =
bx <
bx ;
bx :
bx 9
b0 8
bx 7
b0 6
b0 5
bx 4
b0 3
bx 2
b0 1
b0 0
bx /
b0 .
b0 -
bx ,
bx +
bx *
bx )
bx (
b0 '
b0 &
b0 %
b0 $
b0 #
b0 "
bx !
$end
#1
b0 !
b0 ,
b0 =
b0 (
b0 7
b0 <
b0 *
b0 2
b0 :
b0 )
b0 4
b0 ;
#2
b0 +
b0 /
b0 9
#5
b1 #
b1 &
b1 .
b1 1
b1 3
b1 6
b10 "
b10 %
b10 -
b10 0
b10 5
#6
b1 !
b1 ,
b1 =
b11 (
b11 7
b11 <
b1 )
b1 4
b1 ;
#7
b11 +
b11 /
b11 9
#10
b11 !
b11 ,
b11 =
b1 "
b1 %
b1 -
b1 0
b1 5
b1 $
b1 '
b1 8
#11
b1 *
b1 2
b1 :
b1 (
b1 7
b1 <
#12
b10 !
b10 ,
b10 =
b10 +
b10 /
b10 9
#15
b1 !
b1 ,
b1 =
b11 #
b11 &
b11 .
b11 1
b11 3
b11 6
b1111 "
b1111 %
b1111 -
b1111 0
b1111 5
b10 $
b10 '
b10 8
#16
b11 !
b11 ,
b11 =
b11 *
b11 2
b11 :
b1111 (
b1111 7
b1111 <
b11 )
b11 4
b11 ;
#17
b10010 +
b10010 /
b10010 9
#20
b1111 !
b1111 ,
b1111 =
b1100 #
b1100 &
b1100 .
b1100 1
b1100 3
b1100 6
b1001 "
b1001 %
b1001 -
b1001 0
b1001 5
b11 $
b11 '
b11 8
#21
b1101 !
b1101 ,
b1101 =
b1000 *
b1000 2
b1000 :
b1101 (
b1101 7
b1101 <
b1100 )
b1100 4
b1100 ;
#22
b10101 +
b10101 /
b10101 9
#25
b10101 !
b10101 ,
b10101 =
b1 $
b1 '
b1 8
#30
b101000 "
b101000 %
b101000 -
b101000 0
b101000 5
#31
b101100 (
b101100 7
b101100 <
#32
b110100 !
b110100 ,
b110100 =
b110100 +
b110100 /
b110100 9
#35
b11 #
b11 &
b11 .
b11 1
b11 3
b11 6
#36
b0 *
b0 2
b0 :
b101011 (
b101011 7
b101011 <
b11 )
b11 4
b11 ;
#37
b101011 !
b101011 ,
b101011 =
b101011 +
b101011 /
b101011 9
#40
b0 !
b0 ,
b0 =
b1100 #
b1100 &
b1100 .
b1100 1
b1100 3
b1100 6
b1001 "
b1001 %
b1001 -
b1001 0
b1001 5
b10 $
b10 '
b10 8
#41
b1000 !
b1000 ,
b1000 =
b1000 *
b1000 2
b1000 :
b1101 (
b1101 7
b1101 <
b1100 )
b1100 4
b1100 ;
#42
b10101 +
b10101 /
b10101 9
