Lab05/part1/reg_file.v
module reg_file(IN,OUT1,OUT2,INADDRESS,OUT1ADDRESS,OUT2ADDRESS, WRITE, CLK, RESET);

    input [7:0] IN;
    input [2:0]  INADDRESS, OUT1ADDRESS, OUT2ADDRESS;
    input  WRITE, CLK, RESET;

    output [7:0] OUT1, OUT2;
    reg [7:0] OUT1, OUT2;

    reg [7:0] register0, register1, register2, register3, register4, register5, register6, register7;

    always @(OUT1ADDRESS, register0, register1, register2, register3, register4, register5, register6, register7) begin
        
        case(OUT1ADDRESS)

            3'b000: #2 OUT1 = register0;
            3'b001: #2 OUT1 = register1;
            3'b010: #2 OUT1 = register2;
            3'b011: #2 OUT1 = register3;
            3'b100: #2 OUT1 = register4;
            3'b101: #2 OUT1 = register5;
            3'b110: #2 OUT1 = register6;
            3'b111: #2 OUT1 = register7;

            default:  #2 OUT1 = 0;

        endcase

    end

    always @(OUT2ADDRESS, register0, register1, register2, register3, register4, register5, register6, register7) begin
        
        case(OUT2ADDRESS)

            3'b000: #2 OUT2 = register0;
            3'b001: #2 OUT2 = register1;
            3'b010: #2 OUT2 = register2;
            3'b011: #2 OUT2 = register3;
            3'b100: #2 OUT2 = register4;
            3'b101: #2 OUT2 = register5;
            3'b110: #2 OUT2 = register6;
            3'b111: #2 OUT2 = register7;

            default:  #2 OUT2 = 0;

        endcase

    end

    always @(posedge CLK) begin
        
        if (WRITE && ~RESET) begin
        case(INADDRESS)

            3'b000: #1 register0 = IN;
            3'b001: #1 register1 = IN;
            3'b010: #1 register2 = IN;
            3'b011: #1 register3 = IN;
            3'b100: #1 register4 = IN;
            3'b101: #1 register5 = IN;
            3'b110: #1 register6 = IN;
            3'b111: #1 register7 = IN;
            
            default #1 register0 = 0;

        endcase
        end

        if (RESET) begin
            register0 = 0;
            register1 = 0;
            register2 = 0;
            register3 = 0;
            register4 = 0;
            register5 = 0;
            register6 = 0;
            register7 = 0;
        end

    end

endmodule

Lab05/part2/reg_file_tb.v
// Computer Architecture (CO224) - Lab 05
// Design: Register File of Simple Processor

`include "reg_file.v"

module reg_file_tb;
    
    reg [7:0] WRITEDATA;
    reg [2:0] WRITEREG, READREG1, READREG2;
    reg CLK, RESET, WRITEENABLE; 
    wire [7:0] REGOUT1, REGOUT2;
    
    reg_file regfile(WRITEDATA, REGOUT1, REGOUT2, WRITEREG, READREG1, READREG2, WRITEENABLE, CLK, RESET);

    initial
    $monitor($time, "WRITEDATA = %d | REGOUT1 = %d, REGOUT2 = %d | WRITEREG =  %d, READREG1 = %d, READREG2 = %d | WRITEENABLE = %d, CLK = %d, RESET %d",WRITEDATA, REGOUT1, REGOUT2, WRITEREG, READREG1, READREG2, WRITEENABLE, CLK, RESET);
       
    initial
    begin
        CLK = 1'b1;
        
        // generate files needed to plot the waveform using GTKWave
        $dumpfile("reg_file_wavedata.vcd");
		$dumpvars(0, reg_file_tb);
        
        // assign values with time to input signals to see output 
        RESET = 1'b0;
        WRITEENABLE = 1'b0;
        
        #4
        RESET = 1'b1;
        READREG1 = 3'd0;
        READREG2 = 3'd4;
        
        #6
        RESET = 1'b0;
        
        #2
        WRITEREG = 3'd2;
        WRITEDATA = 8'd95;
        WRITEENABLE = 1'b1;
        
        #7
        WRITEENABLE = 1'b0;
        
        #1
        READREG1 = 3'd2;
        
        #7
        WRITEREG = 3'd1;
        WRITEDATA = 8'd28;
        WRITEENABLE = 1'b1;
        READREG1 = 3'd1;
        
        #8
        WRITEENABLE = 1'b0;
        
        #8
        WRITEREG = 3'd4;
        WRITEDATA = 8'd6;
        WRITEENABLE = 1'b1;
        
        #8
        WRITEDATA = 8'd15;
        WRITEENABLE = 1'b1;
        
        #10
        WRITEENABLE = 1'b0;
        
        #6
        WRITEREG = -3'd1;
        WRITEDATA = 8'd50;
        WRITEENABLE = 1'b1;
        
        #5
        WRITEENABLE = 1'b0;
        
        #10
        $finish;
    end
    
    // clock signal generation
    always
        #4 CLK = ~CLK;
        

endmodule

Lab05/part1/reg_file_wavedata.vcd
$date
	Wed May 03 10:40:57 2023
$end
$version
	Icarus Verilog
$end
$timescale
	1s
$end
$scope module reg_file_tb $end
$var wire 8 ! REGOUT2 [7:0] $end
$var wire 8 " REGOUT1 [7:0] $end
$var reg 1 # CLK $end
$var reg 3 $ READREG1 [2:0] $end
$var reg 3 % READREG2 [2:0] $end
$var reg 1 & RESET $end
$var reg 8 ' WRITEDATA [7:0] $end
$var reg 1 ( WRITEENABLE $end
$var reg 3 ) WRITEREG [2:0] $end
$scope module regfile $end
$var wire 1 # CLK $end
$var wire 8 * IN [7:0] $end
$var wire 3 + INADDRESS [2:0] $end
$var wire 3 , OUT1ADDRESS [2:0] $end
$var wire 3 - OUT2ADDRESS [2:0] $end
$var wire 1 & RESET $end
$var wire 1 ( WRITE $end
$var reg 8 . OUT1 [7:0] $end
$var reg 8 / OUT2 [7:0] $end
$var reg 8 0 register0 [7:0] $end
$var reg 8 1 register1 [7:0] $end
$var reg 8 2 register2 [7:0] $end
$var reg 8 3 register3 [7:0] $end
$var reg 8 4 register4 [7:0] $end
$var reg 8 5 register5 [7:0] $end
$var reg 8 6 register6 [7:0] $end
$var reg 8 7 register7 [7:0] $end
$upscope $end
$upscope $end
$enddefinitions $end
$comment Show the parameter values. $end
$dumpall
$end
#0
$dumpvars
bx 7
bx 6
bx 5
bx 4
bx 3
bx 2
bx 1
bx 0
bx /
bx .
bx -
bx ,
bx +
bx *
bx )
0(
bx '
0&
bx %
bx $
1#
bx "
bx !
$end
#4
0#
b100 %
b100 -
b0 $
b0 ,
1&
#8
b0 7
b0 6
b0 5
b0 4
b0 3
b0 2
b0 1
b0 0
1#
#10
b0 !
b0 /
b0 "
b0 .
0&
#12
1(
b1011111 '
b1011111 *
b10 )
b10 +
0#
#16
1#
#17
b1011111 2
#19
0(
#20
b10 $
b10 ,
0#
#22
b1011111 "
b1011111 .
#24
1#
#27
b1 $
b1 ,
1(
b11100 '
b11100 *
b1 )
b1 +
#28
0#
#29
b0 "
b0 .
#32
1#
#33
b11100 1
#35
b11100 "
b11100 .
0(
#36
0#
#40
1#
#43
1(
b110 '
b110 *
b100 )
b100 +
#44
0#
#48
1#
#49
b110 4
#51
b110 !
b110 /
b1111 '
b1111 *
#52
0#
#56
1#
#57
b1111 4
#59
b1111 !
b1111 /
#60
0#
#61
0(
#64
1#
#67
1(
b110010 '
b110010 *
b111 )
b111 +
#68
0#
#72
1#
0(
