Lab05/part3/alu.v
// CO224 - Lab05 PART-1
// GROUP - 11

// ALU module 
// 8-bit ALU unit, that can operate with two 8-bit numbers to generate the result
// give the relevant output to RESULT respect to SELECT 

// Input:
//      DATA1, DATA2, SELECT
// Output:
//      RESULT

// Operations:
//      FORWARD - forward the data in DATA2 into RESULT 
//      ADD     - add DATA1 and DATA2, give the addiction to RESULT
//      AND     - and DATA1 and DATA2, give the result to RESULT     
//      OR      - or DATA1 and DATA2, give the result to RESULT  

// SELECTION CODE:
//      FOEWARD - 000   
//      ADD     - 001
//      AND     - 010   
//      OR      - 011

module alu(DATA1, DATA2, RESULT, SELECT);

    // initailize input ports
    input [7:0] DATA1, DATA2;
    input [0:2] SELECT;
    // initailize output ports
    output [7:0] RESULT;

    // make wires for connect each module's outputs to the mux
    wire [7:0] forward_result, add_result, and_result, or_result;

    // make instances of for each module
    // FORWARD - alu_forward
    // ADD     - alu_add
    // AND     - alu_and
    // OR      - alu_or
    // connect each module's relevant input and output
    ALU_FORWARD alu_forward(DATA2, forward_result);
    ALU_ADD alu_add(DATA1, DATA2, add_result);
    ALU_AND alu_and(DATA1, DATA2, and_result);
    ALU_OR alu_or(DATA1, DATA2, or_result);

    // instantiation of the mux
    // connect all the the module's output to the mux 
    // select a input as the selection
    MUX mux(forward_result, add_result, and_result, or_result, RESULT, SELECT);

endmodule


// FORWARD module
// used to foward the 8 bit DATA2 directly to output of the module
// Inputs  - DATA2
// Outputs - RESULT
module ALU_FORWARD(DATA2, RESULT);

    // initailize input ports
    input [7:0] DATA2;
    // initailize output ports
    output [7:0] RESULT;

    // assigen the DATA2 value to RESULT with a 1 time unit delay
    assign #1 RESULT = DATA2;

endmodule


// ADD module
// 8 bit adder for add two 8 bit number and give a 8 bit result
// Inputs - DATA1, DATA2
// Output - RESULT
module ALU_ADD(DATA1, DATA2, RESULT);

    // initailize input ports
    input [7:0] DATA1, DATA2;
    // initailize output ports
    output [7:0] RESULT;

    // get the addition of DATA1 and DATA2 
    // assign the value to RESULT with a 2 time units delay
    assign #2 RESULT = DATA1 + DATA2;

endmodule


// AND module
// bitwise AND the give two 8 bit numbers and output a 8 bit number
// Inout  - DATA1, DATA2
// Output - RESULT
module ALU_AND(DATA1, DATA2, RESULT);

    // initailize input ports
    input [7:0] DATA1, DATA2;
    // initailize output ports
    output [7:0] RESULT;

    // AND bitwise each bit
    // assign it to RESULT with a 1 time unit delay
    assign #1 RESULT = DATA1 & DATA2;

endmodule


// OR module
// bitwise OR the give two 8 bit numbers and output a 8 bit number
// Inout  - DATA1, DATA2
// Output - RESULT
module ALU_OR(DATA1, DATA2, RESULT);

    // initailize input ports
    input [7:0] DATA1, DATA2;
    // initailize output ports
    output [7:0] RESULT;

    // and bitwise each bit
    // assign it to RESULT with a 1 time unit delay
    assign #1 RESULT = DATA1 | DATA2;

endmodule


// MUX module
// select a inputs for the inputs
// map it to the ouput reference to the selection bits
// Inputs  - forward_result, add_result, and_result, or_result, SELECT
// Outputs - RESULT
module MUX(forward_result, add_result, and_result, or_result, RESULT, SELECT);

    // initailize input ports
    input [7:0] forward_result, add_result, and_result, or_result;
    input [2:0] SELECT;
    // initailize output ports
    output [7:0] RESULT;
    // initailize the registers
    reg [7:0] RESULT;

    // set a always block to trigger when changing 
    // forward_result, add_result, and_result, or_result, SELECT
    // thus, if these inputs are change the output is change reference to selection bits
    always @(forward_result, add_result, and_result, or_result, SELECT) begin
        
        // case block to check the select bit
        // give the result value 
        case(SELECT)

            // selection for FORWARD
            3'b000 : RESULT = forward_result;
            // selection for ADD
            3'b001 : RESULT = add_result;
            // selection for AND
            3'b010 : RESULT = and_result;
            // selection for OR
            3'b011 : RESULT = or_result;

            // deafult routing
            default : RESULT = 0;
        endcase

    end

endmodule

Lab05/part3/mycpu/modules.v
// CO224 - Lab05 PART-3
// GROUP - 11

// this file contains two's compliment unit and mux unit
// two_comp - get a 8 bit data and output its 2's compliment
// mux - used to select two 8 bit data with a selection bit

// module for get the 2's complwment required for sub instruction
module two_comp(DATA, OUT);

    input [7:0] DATA;
    output [7:0] OUT;
    //assign 2's complement of the data to the output
    assign #1 OUT = ~DATA + 1;

endmodule

//2x1 mux module for transfer data
module mux(DATA1, DATA2, SELECT, OUTPUT);

    input [7:0] DATA1, DATA2; // input data to the mux
    input SELECT; // selector bit
    output reg [7:0] OUTPUT; // output from the mux

    always @(DATA1, DATA2, SELECT) begin 

        if (SELECT) //select= 1, data 2 is selected from the mux
            OUTPUT = DATA2;
        else // else data 1 is selected
            OUTPUT = DATA1;

    end

endmodule

Lab05/part2/reg_file.v
// CO224 - Lab05 PART-1
// GROUP - 11

// REGISTER FILE module
// 8x8 register file that can store 8-bit binary numbers
// register numbers are 0-7
// INPUT ports: 
//     INADDRESS, OUT1ADDRESS, OUT2ADDRESS : 3-bit
//     IN : 8-bit
//     WRITE, CLK, RESET : 1-bit
// OUTPUT ports:
//     OUT1, OUT2 : 8-bit
// Reading  - for given register numbers(OUT1ADDRESS, OUT2ADDRESS), 
//            OUT1 and OUT2 will output the stored value asynchronously
//            reading delay - 2 time unit
// Writting - to a given register numbers(INADDRESS),
//            IN data will write synchronously when a positive clk edge and WRITE is enable
//            writting delay - 1 time unit
// Reset    - when reset is enable, all the register values will reset to 0 in a positive clk edge
module reg_file(IN, OUT1, OUT2, INADDRESS, OUT1ADDRESS, OUT2ADDRESS, WRITE, CLK, RESET);

    // declare input ports
    input [7:0] IN;
    input [2:0]  INADDRESS, OUT1ADDRESS, OUT2ADDRESS;
    input  WRITE, CLK, RESET;

    // declare output ports
    output [7:0] OUT1, OUT2;
    
    // declare the 8-bit, 8 registers
    reg [7:0] registers [7:0];

    // assign block for change the OUT1, in a change of OUT1ADDRESS or register values
    // with a 2 time unit delay
    assign #2 OUT1 = registers[OUT1ADDRESS];

    // assign block for chnage the OUT1, in a change of OUT2ADDRESS or register values
    // with a 2 time unit delay
    assign #2 OUT2 = registers[OUT2ADDRESS];

    // always block for check for a positive clk edge
    // to write a reg or reset registers
    always @(posedge CLK) begin
        
        // to write a register
        // WRITE should be enable and RESET should be desable
        if (WRITE && ~RESET) begin
            
            // select the appropriate reg numbers
            // writting takes 1 time unit time
            case(INADDRESS)

                3'b000: #1 registers[0] = IN; // write IN to register0
                3'b001: #1 registers[1] = IN; // write IN to register1
                3'b010: #1 registers[2] = IN; // write IN to register2
                3'b011: #1 registers[3] = IN; // write IN to register3
                3'b100: #1 registers[4] = IN; // write IN to register4
                3'b101: #1 registers[5] = IN; // write IN to register5
                3'b110: #1 registers[6] = IN; // write IN to register6
                3'b111: #1 registers[7] = IN; // write IN to register7
                
                default #1 registers[0] = IN; // default value

            endcase

            //#1 registers[INADDRESS] = IN;
        end

        // if RESET is enable
        // set all the register values to 0
        if (RESET) begin
            registers[0] = 0; // 0 to register0
            registers[1] = 0; // 0 to register1
            registers[2] = 0; // 0 to register2
            registers[3] = 0; // 0 to register3
            registers[4] = 0; // 0 to register4
            registers[5] = 0; // 0 to register5
            registers[6] = 0; // 0 to register6
            registers[7] = 0; // 0 to register7
        end

    end

endmodule

Lab05/part3/mycpu/control_unit.v
// CO224 - Lab05 PART-3
// GROUP - 11

// Control Unit
// To decode the OpCode and make the control signals

module control_unit(OPCODE, WRITEENABLE, COMP_SELECT, IMMEDIATE_SELECT, ALUOP);

    // declaration of input output retisters
    input [7:0] OPCODE; 
    output reg WRITEENABLE, COMP_SELECT, IMMEDIATE_SELECT; //control signal
    output reg [2:0] ALUOP; // control signal for ALU (2 bit signal)

    // alway block for Opcodes
    always @(OPCODE) begin 

        // delay of the dedcoding
        #1
        //enabling the control signals according to the OPCODE
        case (OPCODE)
            // loadi - load the register with the given immediate value 
            8'b0000_0000: begin
                WRITEENABLE = 1'b1; // control signal to write to the register
                COMP_SELECT = 1'b0; 
                IMMEDIATE_SELECT = 1'b1; // immediate number select
                ALUOP = 3'b000; // select forward result from ALU
            end

            //mov - copy a value in a register to another register
            8'b0000_0001: begin
                WRITEENABLE = 1'b1;
                COMP_SELECT = 1'b0;
                IMMEDIATE_SELECT = 1'b0;
                ALUOP = 3'b000;
            end

            // add - add 2 register values and write the result to another register
            8'b0000_0010: begin
                WRITEENABLE = 1'b1;
                COMP_SELECT = 1'b0;
                IMMEDIATE_SELECT = 1'b0;
                ALUOP = 3'b001; //select add result from alu
            end

            // sub - subtract 2 reg values and write the result to another register
            8'b0000_0011: begin
                WRITEENABLE = 1'b1;
                COMP_SELECT = 1'b1; // 2s complement enables(input for aku module is 2's complemented)
                IMMEDIATE_SELECT = 1'b0;
                ALUOP = 3'b001; // select add from ALU
            end

            // and - bitwise AND of 2 reg values
            8'b0000_0100: begin
                WRITEENABLE = 1'b1;
                COMP_SELECT = 1'b0;
                IMMEDIATE_SELECT = 1'b0;
                ALUOP = 3'b010; // select and result form alu
            end

            // or - bitwise OR of 2 reg values
            8'b0000_0101: begin
                WRITEENABLE = 1'b1;
                COMP_SELECT = 1'b0;
                IMMEDIATE_SELECT = 1'b0;
                ALUOP = 3'b011; // select or result from ALU
            end

        endcase

    end

endmodule

Lab05/part3/mycpu/pc.v
// CO224 - Lab05 PART-3
// GROUP - 11

// program counter module
module pc(RESET, CLK, PC);

    input RESET, CLK;
    output reg [31:0] PC; // reg to hold the address of the current executing instruction
    
    reg [31:0] PC_NEXT; // next instruction to be executed
    wire [31:0] adder_out; // address of the next instruction to be executed

    // output from the PC adder (adderout = PC+4)
    pc_add pc_adder(PC, adder_out);

    always @(adder_out) // if pc adder output changes, adder out is assigned to the next instruction address 
    PC_NEXT = adder_out;

    always @(posedge CLK) begin
        // at every positive edge of the clock
        // if reset is enabled, 0 is written to PC
        // else Next address is written to PC 
        if (RESET)
            #1 PC = 32'b00000000000000000000000000000000;
        else
            #1 PC = PC_NEXT;
    end 

endmodule

//pc adder module (adder_out = PC+4(because word size is 4 bytes))
module pc_add(PC, adder_out);

    // declare ports
    input [31:0] PC;
    output [31:0] adder_out;

    // Incremtn the value by 4 and assing it the output with a delay of 1
    assign #1 adder_out = PC + 4 ;

endmodule

Lab05/part3/mycpu/cpu.v
// CO224 - Lab05 PART-3
// GROUP - 11

// include modules 
`include "alu.v"
`include "reg_file.v"
`include "pc.v"
`include "control_unit.v"
`include "modules.v"


// cpu module 
// that has the capacity to execute a give instruction from the instruction memory

// Inputs :
//          INSTRUCTION, CLK, RESET
// Output :
//          PC  

//cpu module
module cpu(PC, INSTRUCTION, CLK, RESET);

    input CLK, RESET;   // Clock and Reset
    input [31:0] INSTRUCTION; // instruction array

    output [31:0] PC; // address of the current executing instruction

    wire [2:0] ALUOP; //select bit of ALU
    wire WRITEENABLE, MUXSELECT1, MUXSELECT2; // control signals
    wire [7:0] ALURESULT, REGOUT2, REGOUT1, COMPOUT, MUXOUT1, MUXOUT2, IMMEDIATE, OPCODE; // declare the weires

    // extract the immediate from the instruction
    assign IMMEDIATE = INSTRUCTION[7:0];
    // extract the opcode from the instruction
    assign OPCODE = INSTRUCTION[31:24];

    //initialization of sub modules
    pc Pc(RESET, CLK, PC);  // initialization of Pc
    control_unit Control_Unit(OPCODE, WRITEENABLE, MUXSELECT1, MUXSELECT2, ALUOP); // initialization of Control Unit
    reg_file Reg_File(ALURESULT, REGOUT1, REGOUT2, INSTRUCTION[18:16], INSTRUCTION[10:8], INSTRUCTION[2:0], WRITEENABLE, CLK,RESET);    // initialization of register files
    two_comp Two_Com(REGOUT2, COMPOUT); // initialization of the twos compliment circuit

    // initialization of mux that use to select reg value or the two's compliment of reg value
    mux Mux1(REGOUT2, COMPOUT, MUXSELECT1, MUXOUT1);   
    // initialization of mux that use to select regster reading value or immediate values
    mux Mux2(MUXOUT1, IMMEDIATE, MUXSELECT2, MUXOUT2);

    // declare the alu unit
    alu Alu(REGOUT1, MUXOUT2, ALURESULT, ALUOP);

    // always @(INSTRUCTION, MUXOUT2, MUXSELECT2)
    // $display($time, " %d %d %d", INSTRUCTION[7:0], MUXOUT2, MUXSELECT2);

endmodule

Lab05/part3/mycpu/cpu_tb.v
// Computer Architecture (CO224) - Lab 05
// Design: Testbench of Integrated CPU of Simple Processor
// Author: Isuru Nawinne

`include "cpu.v"

module cpu_tb;

    reg CLK, RESET;
    wire [31:0] PC;
    // wire [31:0] INSTRUCTION;
    reg [31:0] INSTRUCTION;
    
    /* 
    ------------------------
     SIMPLE INSTRUCTION MEM
    ------------------------
    */
    
    // TODO: Initialize an array of registers (8x1024) named 'instr_mem' to be used as instruction memory
    reg [7:0] instr_mem [1023:0];

    
    
    // TODO: Create combinational logic to support CPU instruction fetching, given the Program Counter(PC) value 
    //       (make sure you include the delay for instruction fetching here)

    always @(PC) begin
        #2
        INSTRUCTION[31:24] = instr_mem[PC-1];
        INSTRUCTION[23:16] = instr_mem[PC-2];
        INSTRUCTION[15:8] = instr_mem[PC-3];
        INSTRUCTION[7:0] = instr_mem[PC-4];

    end
    
    initial
    begin
        // Initialize instruction memory with the set of instructions you need execute on CPU
        
        // METHOD 1: manually loading instructions to instr_mem
        // {instr_mem[10'd3], instr_mem[10'd2], instr_mem[10'd1], instr_mem[10'd0]} = 32'b00000000000001000000000000000101;
        // {instr_mem[10'd7], instr_mem[10'd6], instr_mem[10'd5], instr_mem[10'd4]} = 32'b00000000000000100000000000001001;
        // {instr_mem[10'd11], instr_mem[10'd10], instr_mem[10'd9], instr_mem[10'd8]} = 32'b00000010000001100000010000000010;
        
        // METHOD 2: loading instr_mem content from instr_mem.mem file
        $readmemb("instr_mem.mem", instr_mem);
    end
    
    /* 
    -----
     CPU
    -----
    */
    cpu mycpu(PC, INSTRUCTION, CLK, RESET);

    initial
    begin
    
        // generate files needed to plot the waveform using GTKWave
        $dumpfile("cpu_wavedata.vcd");
		$dumpvars(0, cpu_tb);
        
        CLK = 1'b0;
        RESET = 1'b0;
        
        // TODO: Reset the CPU (by giving a pulse to RESET signal) to start the program execution
        
        // finish simulation after some time
        #100
        $finish;
        
    end
    
    // clock signal generation
    always
    #4 CLK = ~CLK;

    initial begin
        $monitor($time, " %b %b %b %b", PC, INSTRUCTION, CLK, RESET);
        #200 RESET = 1; 
        #5 RESET = 0;
    end
        

endmodule

Lab05/part3/mycpu/cpu_wavedata.vcd
$date
	Wed May 24 09:41:17 2023
$end
$version
	Icarus Verilog
$end
$timescale
	1s
$end
$scope module cpu_tb $end
$var wire 32 ! PC [31:0] $end
$var reg 1 " CLK $end
$var reg 32 # INSTRUCTION [31:0] $end
$var reg 1 $ RESET $end
$scope module mycpu $end
$var wire 1 " CLK $end
$var wire 32 % INSTRUCTION [31:0] $end
$var wire 1 $ RESET $end
$var wire 1 & WRITEENABLE $end
$var wire 8 ' REGOUT2 [7:0] $end
$var wire 8 ( REGOUT1 [7:0] $end
$var wire 32 ) PC [31:0] $end
$var wire 8 * OPCODE [7:0] $end
$var wire 1 + MUXSELECT2 $end
$var wire 1 , MUXSELECT1 $end
$var wire 8 - MUXOUT2 [7:0] $end
$var wire 8 . MUXOUT1 [7:0] $end
$var wire 8 / IMMEDIATE [7:0] $end
$var wire 8 0 COMPOUT [7:0] $end
$var wire 8 1 ALURESULT [7:0] $end
$var wire 3 2 ALUOP [2:0] $end
$scope module Alu $end
$var wire 8 3 or_result [7:0] $end
$var wire 8 4 forward_result [7:0] $end
$var wire 8 5 and_result [7:0] $end
$var wire 8 6 add_result [7:0] $end
$var wire 3 7 SELECT [0:2] $end
$var wire 8 8 RESULT [7:0] $end
$var wire 8 9 DATA2 [7:0] $end
$var wire 8 : DATA1 [7:0] $end
$upscope $end
$scope module Control_Unit $end
$var wire 8 ; OPCODE [7:0] $end
$var reg 3 < ALUOP [2:0] $end
$var reg 1 , COMP_SELECT $end
$var reg 1 + IMMEDIATE_SELECT $end
$var reg 1 & WRITEENABLE $end
$upscope $end
$scope module Mux1 $end
$var wire 1 , SELECT $end
$var wire 8 = DATA2 [7:0] $end
$var wire 8 > DATA1 [7:0] $end
$var reg 8 ? OUTPUT [7:0] $end
$upscope $end
$scope module Mux2 $end
$var wire 8 @ DATA1 [7:0] $end
$var wire 8 A DATA2 [7:0] $end
$var wire 1 + SELECT $end
$var reg 8 B OUTPUT [7:0] $end
$upscope $end
$scope module Pc $end
$var wire 1 " CLK $end
$var wire 1 $ RESET $end
$var wire 32 C adder_out [31:0] $end
$var reg 32 D PC [31:0] $end
$var reg 32 E PC_NEXT [31:0] $end
$upscope $end
$scope module Reg_File $end
$var wire 1 " CLK $end
$var wire 8 F IN [7:0] $end
$var wire 3 G INADDRESS [2:0] $end
$var wire 8 H OUT1 [7:0] $end
$var wire 3 I OUT1ADDRESS [2:0] $end
$var wire 8 J OUT2 [7:0] $end
$var wire 3 K OUT2ADDRESS [2:0] $end
$var wire 1 $ RESET $end
$var wire 1 & WRITE $end
$upscope $end
$scope module Two_Com $end
$var wire 8 L DATA [7:0] $end
$var wire 8 M OUT [7:0] $end
$upscope $end
$upscope $end
$upscope $end
$scope module cpu_tb $end
$scope module mycpu $end
$scope module Reg_File $end
$var reg 8 N \registers[0] [7:0] $end
$upscope $end
$upscope $end
$upscope $end
$scope module cpu_tb $end
$scope module mycpu $end
$scope module Reg_File $end
$var reg 8 O \registers[1] [7:0] $end
$upscope $end
$upscope $end
$upscope $end
$scope module cpu_tb $end
$scope module mycpu $end
$scope module Reg_File $end
$var reg 8 P \registers[2] [7:0] $end
$upscope $end
$upscope $end
$upscope $end
$scope module cpu_tb $end
$scope module mycpu $end
$scope module Reg_File $end
$var reg 8 Q \registers[3] [7:0] $end
$upscope $end
$upscope $end
$upscope $end
$scope module cpu_tb $end
$scope module mycpu $end
$scope module Reg_File $end
$var reg 8 R \registers[4] [7:0] $end
$upscope $end
$upscope $end
$upscope $end
$scope module cpu_tb $end
$scope module mycpu $end
$scope module Reg_File $end
$var reg 8 S \registers[5] [7:0] $end
$upscope $end
$upscope $end
$upscope $end
$scope module cpu_tb $end
$scope module mycpu $end
$scope module Reg_File $end
$var reg 8 T \registers[6] [7:0] $end
$upscope $end
$upscope $end
$upscope $end
$scope module cpu_tb $end
$scope module mycpu $end
$scope module Reg_File $end
$var reg 8 U \registers[7] [7:0] $end
$upscope $end
$upscope $end
$upscope $end
$enddefinitions $end
$comment Show the parameter values. $end
$dumpall
$end
#0
$dumpvars
bx U
bx T
bx S
bx R
bx Q
bx P
bx O
bx N
bx M
bx L
bx K
bx J
bx I
bx H
bx G
bx F
bx E
bx D
bx C
bx B
bx A
bx @
bx ?
bx >
bx =
bx <
bx ;
bx :
bx 9
bx 8
bx 7
bx 6
bx 5
bx 4
bx 3
bx 2
bx 1
bx 0
bx /
bx .
bx -
x,
x+
bx *
bx )
bx (
bx '
x&
bx %
1$
bx #
0"
bx !
$end
#4
1"
#5
b0 !
b0 )
b0 D
b0 U
b0 T
b0 S
b0 R
b0 Q
b0 P
b0 O
b0 N
0$
#6
b100 E
b100 C
#7
b101 /
b101 A
b101 K
b0 I
b0 G
b0 *
b0 ;
b101 #
b101 %
#8
b101 -
b101 9
b101 B
b0 2
b0 7
b0 <
1+
0,
1&
0"
#9
b101 1
b101 8
b101 F
b0 .
b0 ?
b0 @
bx1x1 3
b0x0x 5
b101 4
b0 '
b0 >
b0 J
b0 L
b0 (
b0 :
b0 H
#10
b0 0
b0 =
b0 M
b101 3
b0 5
#11
b101 6
#12
1"
#13
b101 N
b100 !
b100 )
b100 D
#14
b1000 E
b1000 C
#15
b1001 -
b1001 9
b1001 B
b1001 /
b1001 A
b1 K
b1 G
b10000000000001001 #
b10000000000001001 %
b101 (
b101 :
b101 H
#16
b1001 1
b1001 8
b1001 F
b1101 3
b1001 4
b1 5
0"
#17
b1110 6
#20
1"
#21
b1000 !
b1000 )
b1000 D
b1001 O
#22
b1100 E
b1100 C
#23
b1 -
b1 9
b1 B
b1 /
b1 A
b10 G
b1 *
b1 ;
b1001 .
b1001 ?
b1001 @
b1000000100000000000000001 #
b1000000100000000000000001 %
b1001 '
b1001 >
b1001 J
b1001 L
#24
b1001 -
b1001 9
b1001 B
b1 1
b1 8
b1 F
b101 3
0+
b1 4
b11110111 0
b11110111 =
b11110111 M
0"
#25
b1001 1
b1001 8
b1001 F
b1101 3
b1001 4
#28
1"
#29
b1001 P
b1100 !
b1100 )
b1100 D
#30
b10000 E
b10000 C
#31
b0 /
b0 A
b0 K
b10 I
b11 G
b10 *
b10 ;
b10000000110000001000000000 #
b10000000110000001000000000 %
#32
b1110 1
b1110 8
b1110 F
b1 2
b1 7
b1 <
0"
#33
b101 -
b101 9
b101 B
b101 .
b101 ?
b101 @
b101 '
b101 >
b101 J
b101 L
b1001 (
b1001 :
b1001 H
#34
b101 4
b11111011 0
b11111011 =
b11111011 M
#36
1"
#37
b10000 !
b10000 )
b10000 D
b1110 Q
#38
b10100 E
b10100 C
#39
b1 /
b1 A
b1 K
b11 I
b100 G
b11 *
b11 ;
b11000001000000001100000001 #
b11000001000000001100000001 %
#40
b11111011 -
b11111011 9
b11111011 B
b11111011 .
b11111011 ?
b11111011 @
1,
0"
#41
b11111011 3
b1001 5
b11111011 4
b1001 '
b1001 >
b1001 J
b1001 L
b1110 (
b1110 :
b1110 H
#42
b11110111 -
b11110111 9
b11110111 B
b11110111 .
b11110111 ?
b11110111 @
b11110111 0
b11110111 =
b11110111 M
b11111111 3
b1010 5
#43
b110 5
b11110111 4
#44
b101 1
b101 8
b101 F
b101 6
1"
#45
b101 R
b10100 !
b10100 )
b10100 D
#46
b11000 E
b11000 C
#47
b1110101 /
b1110101 A
b101 K
b0 I
b0 G
b0 *
b0 ;
b1110101 #
b1110101 %
#48
b11110111 1
b11110111 8
b11110111 F
b1110101 -
b1110101 9
b1110101 B
b1001 .
b1001 ?
b1001 @
b0 2
b0 7
b0 <
1+
0,
0"
#49
b1110101 1
b1110101 8
b1110101 F
b0 .
b0 ?
b0 @
b1111111 3
b100 5
b1110101 4
b0 '
b0 >
b0 J
b0 L
b101 (
b101 :
b101 H
#50
b0 0
b0 =
b0 M
b1110101 3
b101 5
#51
b1111010 6
#52
1"
#53
b11000 !
b11000 )
b11000 D
b1110101 N
#54
b11100 E
b11100 C
#55
b10010010 -
b10010010 9
b10010010 B
b10010010 /
b10010010 A
b10 K
b1 G
b10000000010010010 #
b10000000010010010 %
b1110101 (
b1110101 :
b1110101 H
#56
b10010010 1
b10010010 8
b10010010 F
b11110111 3
b10010010 4
b10000 5
0"
#57
b1001 .
b1001 ?
b1001 @
b1001 '
b1001 >
b1001 J
b1001 L
b111 6
#58
b11110111 0
b11110111 =
b11110111 M
#60
1"
#61
b10010010 O
b11100 !
b11100 )
b11100 D
#62
b100000 E
b100000 C
#63
b0 -
b0 9
b0 B
b0 /
b0 A
b0 K
b1 I
b101 G
b100 *
b100 ;
b100000001010000000100000000 #
b100000001010000000100000000 %
#64
b0 1
b0 8
b0 F
b1001 -
b1001 9
b1001 B
b1110101 3
b0 5
b0 4
b10 2
b10 7
b10 <
0+
0"
#65
b1110101 -
b1110101 9
b1110101 B
b1 1
b1 8
b1 F
b1110101 .
b1110101 ?
b1110101 @
b1111101 3
b1 5
b1001 4
b1110101 '
b1110101 >
b1110101 J
b1110101 L
b10010010 (
b10010010 :
b10010010 H
#66
b10000 1
b10000 8
b10000 F
b1110101 4
b10001011 0
b10001011 =
b10001011 M
b11110111 3
b10000 5
#68
1"
#69
b100000 !
b100000 )
b100000 D
b10000 S
#70
b100100 E
b100100 C
#71
b10 /
b10 A
b10 K
b101 I
b110 G
b101 *
b101 ;
b101000001100000010100000010 #
b101000001100000010100000010 %
#72
b11110111 1
b11110111 8
b11110111 F
b11 2
b11 7
b11 <
0"
#73
b1001 -
b1001 9
b1001 B
b1001 .
b1001 ?
b1001 @
b1001 '
b1001 >
b1001 J
b1001 L
b10000 (
b10000 :
b10000 H
#74
b11001 1
b11001 8
b11001 F
b0 5
b1001 4
b11110111 0
b11110111 =
b11110111 M
b11001 3
#75
b11001 6
#76
1"
#77
b11001 T
b100100 !
b100100 )
b100100 D
#78
b101000 E
b101000 C
#79
bx /
bx A
bx K
bx I
bx G
bx *
bx ;
bx #
bx %
#80
0"
#81
bx -
bx 9
bx B
bx .
bx ?
bx @
bx '
bx >
bx J
bx L
bx (
bx :
bx H
#82
bx 1
bx 8
bx F
bx 4
bx 0
bx =
bx M
bx 3
bx 5
#83
bx 6
#84
1"
#85
b101000 !
b101000 )
b101000 D
#86
b101100 E
b101100 C
#88
0"
#92
1"
#93
b101100 !
b101100 )
b101100 D
#94
b110000 E
b110000 C
#96
0"
#100
1"
#101
b110000 !
b110000 )
b110000 D
#102
b110100 E
b110100 C
