Lab05/part3/alu.v
// CO224 - Lab05 PART-1
// GROUP - 11

// ALU module 
// 8-bit ALU unit, that can operate with two 8-bit numbers to generate the result
// give the relevant output to RESULT respect to SELECT 

// Input:
//      DATA1, DATA2, SELECT
// Output:
//      RESULT

// Operations:
//      FORWARD - forward the data in DATA2 into RESULT 
//      ADD     - add DATA1 and DATA2, give the addiction to RESULT
//      AND     - and DATA1 and DATA2, give the result to RESULT     
//      OR      - or DATA1 and DATA2, give the result to RESULT  

// SELECTION CODE:
//      FOEWARD - 000   
//      ADD     - 001
//      AND     - 010   
//      OR      - 011

module alu(DATA1, DATA2, RESULT, SELECT);

    // initailize input ports
    input [7:0] DATA1, DATA2;
    input [0:2] SELECT;
    // initailize output ports
    output [7:0] RESULT;

    // make wires for connect each module's outputs to the mux
    wire [7:0] forward_result, add_result, and_result, or_result;

    // make instances of for each module
    // FORWARD - alu_forward
    // ADD     - alu_add
    // AND     - alu_and
    // OR      - alu_or
    // connect each module's relevant input and output
    ALU_FORWARD alu_forward(DATA2, forward_result);
    ALU_ADD alu_add(DATA1, DATA2, add_result);
    ALU_AND alu_and(DATA1, DATA2, and_result);
    ALU_OR alu_or(DATA1, DATA2, or_result);

    // instantiation of the mux
    // connect all the the module's output to the mux 
    // select a input as the selection
    MUX mux(forward_result, add_result, and_result, or_result, RESULT, SELECT);

endmodule


// FORWARD module
// used to foward the 8 bit DATA2 directly to output of the module
// Inputs  - DATA2
// Outputs - RESULT
module ALU_FORWARD(DATA2, RESULT);

    // initailize input ports
    input [7:0] DATA2;
    // initailize output ports
    output [7:0] RESULT;

    // assigen the DATA2 value to RESULT with a 1 time unit delay
    assign #1 RESULT = DATA2;

endmodule


// ADD module
// 8 bit adder for add two 8 bit number and give a 8 bit result
// Inputs - DATA1, DATA2
// Output - RESULT
module ALU_ADD(DATA1, DATA2, RESULT);

    // initailize input ports
    input [7:0] DATA1, DATA2;
    // initailize output ports
    output [7:0] RESULT;

    // get the addition of DATA1 and DATA2 
    // assign the value to RESULT with a 2 time units delay
    assign #2 RESULT = DATA1 + DATA2;

endmodule


// AND module
// bitwise AND the give two 8 bit numbers and output a 8 bit number
// Inout  - DATA1, DATA2
// Output - RESULT
module ALU_AND(DATA1, DATA2, RESULT);

    // initailize input ports
    input [7:0] DATA1, DATA2;
    // initailize output ports
    output [7:0] RESULT;

    // AND bitwise each bit
    // assign it to RESULT with a 1 time unit delay
    assign #1 RESULT = DATA1 & DATA2;

endmodule


// OR module
// bitwise OR the give two 8 bit numbers and output a 8 bit number
// Inout  - DATA1, DATA2
// Output - RESULT
module ALU_OR(DATA1, DATA2, RESULT);

    // initailize input ports
    input [7:0] DATA1, DATA2;
    // initailize output ports
    output [7:0] RESULT;

    // and bitwise each bit
    // assign it to RESULT with a 1 time unit delay
    assign #1 RESULT = DATA1 | DATA2;

endmodule


// MUX module
// select a inputs for the inputs
// map it to the ouput reference to the selection bits
// Inputs  - forward_result, add_result, and_result, or_result, SELECT
// Outputs - RESULT
module MUX(forward_result, add_result, and_result, or_result, RESULT, SELECT);

    // initailize input ports
    input [7:0] forward_result, add_result, and_result, or_result;
    input [2:0] SELECT;
    // initailize output ports
    output [7:0] RESULT;
    // initailize the registers
    reg [7:0] RESULT;

    // set a always block to trigger when changing 
    // forward_result, add_result, and_result, or_result, SELECT
    // thus, if these inputs are change the output is change reference to selection bits
    always @(forward_result, add_result, and_result, or_result, SELECT) begin
        
        // case block to check the select bit
        // give the result value 
        case(SELECT)

            // selection for FORWARD
            3'b000 : RESULT = forward_result;
            // selection for ADD
            3'b001 : RESULT = add_result;
            // selection for AND
            3'b010 : RESULT = and_result;
            // selection for OR
            3'b011 : RESULT = or_result;

            // deafult routing
            default : RESULT = 0;
        endcase

    end

endmodule

Lab05/part3/mycpu/modules.v
module two_comp(DATA, OUT);

    input [7:0] DATA;
    output [7:0] OUT;

    assign #1 OUT = ~DATA + 1;

endmodule


module mux(DATA1, DATA2, SELECT, OUTPUT);

    input [7:0] DATA1, DATA2;
    input SELECT;
    output reg [7:0] OUTPUT;

    always @(DATA1, DATA2, SELECT) begin 

        if (SELECT) 
            OUTPUT = DATA2;
        else
            OUTPUT = DATA1;

    end

    always @(DATA1, DATA2, SELECT, OUTPUT)
    $display($time, " >> %d %d %d %d", DATA1, DATA2, SELECT, OUTPUT);
    

endmodule

Lab05/part2/reg_file.v
// CO224 - Lab05 PART-1
// GROUP - 11

// REGISTER FILE module
// 8x8 register file that can store 8-bit binary numbers
// register numbers are 0-7
// INPUT ports: 
//     INADDRESS, OUT1ADDRESS, OUT2ADDRESS : 3-bit
//     IN : 8-bit
//     WRITE, CLK, RESET : 1-bit
// OUTPUT ports:
//     OUT1, OUT2 : 8-bit
// Reading  - for given register numbers(OUT1ADDRESS, OUT2ADDRESS), 
//            OUT1 and OUT2 will output the stored value asynchronously
//            reading delay - 2 time unit
// Writting - to a given register numbers(INADDRESS),
//            IN data will write synchronously when a positive clk edge and WRITE is enable
//            writting delay - 1 time unit
// Reset    - when reset is enable, all the register values will reset to 0 in a positive clk edge
module reg_file(IN, OUT1, OUT2, INADDRESS, OUT1ADDRESS, OUT2ADDRESS, WRITE, CLK, RESET);

    // declare input ports
    input [7:0] IN;
    input [2:0]  INADDRESS, OUT1ADDRESS, OUT2ADDRESS;
    input  WRITE, CLK, RESET;

    // declare output ports
    output [7:0] OUT1, OUT2;
    
    // declare the 8-bit, 8 registers
    reg [7:0] registers [7:0];

    // assign block for change the OUT1, in a change of OUT1ADDRESS or register values
    // with a 2 time unit delay
    assign #2 OUT1 = registers[OUT1ADDRESS];

    // assign block for chnage the OUT1, in a change of OUT2ADDRESS or register values
    // with a 2 time unit delay
    assign #2 OUT2 = registers[OUT2ADDRESS];

    // always block for check for a positive clk edge
    // to write a reg or reset registers
    always @(posedge CLK) begin
        
        // to write a register
        // WRITE should be enable and RESET should be desable
        if (WRITE && ~RESET) begin
            
            // select the appropriate reg numbers
            // writting takes 1 time unit time
            case(INADDRESS)

                3'b000: #1 registers[0] = IN; // write IN to register0
                3'b001: #1 registers[1] = IN; // write IN to register1
                3'b010: #1 registers[2] = IN; // write IN to register2
                3'b011: #1 registers[3] = IN; // write IN to register3
                3'b100: #1 registers[4] = IN; // write IN to register4
                3'b101: #1 registers[5] = IN; // write IN to register5
                3'b110: #1 registers[6] = IN; // write IN to register6
                3'b111: #1 registers[7] = IN; // write IN to register7
                
                default #1 registers[0] = IN; // default value

            endcase

            //#1 registers[INADDRESS] = IN;
        end

        // if RESET is enable
        // set all the register values to 0
        if (RESET) begin
            registers[0] = 0; // 0 to register0
            registers[1] = 0; // 0 to register1
            registers[2] = 0; // 0 to register2
            registers[3] = 0; // 0 to register3
            registers[4] = 0; // 0 to register4
            registers[5] = 0; // 0 to register5
            registers[6] = 0; // 0 to register6
            registers[7] = 0; // 0 to register7
        end

    end

endmodule

Lab05/part3/mycpu/control_unit.v
// CO224 - Lab05 PART-3
// GROUP - 11

// Control Unit
// To decode the OpCode and make the control signals

module control_unit(OPCODE, WRITEENABLE, COMP_SELECT, IMMEDIATE_SELECT, ALUOP);

    // declaration of input output retisters
    input [7:0] OPCODE; 
    output reg WRITEENABLE, COMP_SELECT, IMMEDIATE_SELECT; //control signal
    output reg [2:0] ALUOP; // control signal for ALU (2 bit signal)

    // alway block for Opcodes
    always @(OPCODE) begin 

        // delay of the dedcoding
        #1
        //enabling the control signals according to the OPCODE
        case (OPCODE)
            // loadi - load the register with the given immediate value 
            8'b0000_0000: begin
                WRITEENABLE = 1'b1; // control signal to write to the register
                COMP_SELECT = 1'b0; 
                IMMEDIATE_SELECT = 1'b1; // immediate number select
                ALUOP = 3'b000; // select forward result from ALU
            end

            //mov - copy a value in a register to another register
            8'b0000_0001: begin
                WRITEENABLE = 1'b1;
                COMP_SELECT = 1'b0;
                IMMEDIATE_SELECT = 1'b0;
                ALUOP = 3'b000;
            end

            // add - add 2 register values and write the result to another register
            8'b0000_0010: begin
                WRITEENABLE = 1'b1;
                COMP_SELECT = 1'b0;
                IMMEDIATE_SELECT = 1'b0;
                ALUOP = 3'b001; //select add result from alu
            end

            // sub - subtract 2 reg values and write the result to another register
            8'b0000_0011: begin
                WRITEENABLE = 1'b1;
                COMP_SELECT = 1'b1; // 2s complement enables(input for aku module is 2's complemented)
                IMMEDIATE_SELECT = 1'b0;
                ALUOP = 3'b001; // select add from ALU
            end

            // and - bitwise AND of 2 reg values
            8'b0000_0100: begin
                WRITEENABLE = 1'b1;
                COMP_SELECT = 1'b0;
                IMMEDIATE_SELECT = 1'b0;
                ALUOP = 3'b010; // select and result form alu
            end

            // or - bitwise OR of 2 reg values
            8'b0000_0101: begin
                WRITEENABLE = 1'b1;
                COMP_SELECT = 1'b0;
                IMMEDIATE_SELECT = 1'b0;
                ALUOP = 3'b011; // select or result from ALU
            end

        endcase

    end

endmodule

Lab05/part3/mycpu/pc.v
module pc(RESET, CLK, PC);

    input RESET, CLK;
    output reg [31:0] PC;
    
    reg [31:0] PC_NEXT;
    wire [31:0] adder_out;

    pc_add pc_adder(PC, adder_out);

    initial
    #1 PC = 0;

    always @(adder_out)
    PC_NEXT = adder_out;

    always @(posedge CLK) begin

        if (RESET)
            #1 PC = 32'b00000000000000000000000000000100;
        else
            #1 PC = PC_NEXT;

    end 

endmodule

module pc_add(PC, adder_out);

    input [31:0] PC;
    output [31:0] adder_out;

    assign #1 adder_out = PC + 4 ;

endmodule

Lab05/part3/mycpu/cpu.v
// CO224 - Lab05 PART-3
// GROUP - 11

// include modules 
`include "alu.v"
`include "reg_file.v"
`include "pc.v"
`include "control_unit.v"
`include "modules.v"


// cpu module 
// that has the capacity to execute a give instruction from the instruction memory

// Inputs :
//          INSTRUCTION, CLK, RESET
// Output :
//          PC  

//cpu module
module cpu(PC, INSTRUCTION, CLK, RESET);

    input CLK, RESET;
    input [31:0] INSTRUCTION; // instruction array

    output [31:0] PC; // address of the current executing instruction

    wire [2:0] ALUOP; //select bit of ALU
    wire WRITEENABLE, COMPSELECT, IMMEDIATESELECT; // control signals
    wire [7:0] ALURESULT, REGOUT2, REGOUT1, COMPOUT, MUX1, ALUIN; // 

    //initialization of sub modules
    pc Pc(RESET, CLK, PC);
    control_unit Control_Unit(INSTRUCTION[31:24], WRITEENABLE, COMPSELECT, IMMEDIATESELECT, ALUOP);
    reg_file Reg_File(ALURESULT, REGOUT1, REGOUT2, INSTRUCTION[18:16], INSTRUCTION[10:8], INSTRUCTION[2:0], WRITEENABLE, CLK,RESET);
    two_comp Two_Com(REGOUT2, COMPOUT);

    mux Mux1(REGOUT2, COMPOUT, COMPSELECT, MUX1);
    mux Mux2(MUX1, INSTRUCTION[7:0], IMMEDIATESELECT, ALUIN);

    alu Alu(REGOUT1, ALUIN, ALURESULT, ALUOP);

    // always @(INSTRUCTION, ALUIN, IMMEDIATESELECT)
    // $display($time, " %d %d %d", INSTRUCTION[7:0], ALUIN, IMMEDIATESELECT);

endmodule

Lab05/part3/mycpu/cpu_tb.v
// Computer Architecture (CO224) - Lab 05
// Design: Testbench of Integrated CPU of Simple Processor
// Author: Isuru Nawinne

`include "cpu.v"

module cpu_tb;

    reg CLK, RESET;
    wire [31:0] PC;
    // wire [31:0] INSTRUCTION;
    reg [31:0] INSTRUCTION;
    
    /* 
    ------------------------
     SIMPLE INSTRUCTION MEM
    ------------------------
    */
    
    // TODO: Initialize an array of registers (8x1024) named 'instr_mem' to be used as instruction memory
    reg [7:0] instr_mem [1023:0];

    
    
    // TODO: Create combinational logic to support CPU instruction fetching, given the Program Counter(PC) value 
    //       (make sure you include the delay for instruction fetching here)

    always @(PC) begin
        #2
        INSTRUCTION[31:24] = instr_mem[PC-1];
        INSTRUCTION[23:16] = instr_mem[PC-2];
        INSTRUCTION[15:8] = instr_mem[PC-3];
        INSTRUCTION[7:0] = instr_mem[PC-4];

    end
    
    initial
    begin
        // Initialize instruction memory with the set of instructions you need execute on CPU
        
        // METHOD 1: manually loading instructions to instr_mem
        // {instr_mem[10'd3], instr_mem[10'd2], instr_mem[10'd1], instr_mem[10'd0]} = 32'b00000000000001000000000000000101;
        // {instr_mem[10'd7], instr_mem[10'd6], instr_mem[10'd5], instr_mem[10'd4]} = 32'b00000000000000100000000000001001;
        // {instr_mem[10'd11], instr_mem[10'd10], instr_mem[10'd9], instr_mem[10'd8]} = 32'b00000010000001100000010000000010;
        
        // METHOD 2: loading instr_mem content from instr_mem.mem file
        $readmemb("instr_mem.mem", instr_mem);
    end
    
    /* 
    -----
     CPU
    -----
    */
    cpu mycpu(PC, INSTRUCTION, CLK, RESET);

    initial
    begin
    
        // generate files needed to plot the waveform using GTKWave
        $dumpfile("cpu_wavedata.vcd");
		$dumpvars(0, cpu_tb);
        
        CLK = 1'b0;
        RESET = 1'b0;
        
        // TODO: Reset the CPU (by giving a pulse to RESET signal) to start the program execution
        
        // finish simulation after some time
        #100
        $finish;
        
    end
    
    // clock signal generation
    always
    #4 CLK = ~CLK;

    initial begin
        $monitor($time, " %b %b %b %b", PC, INSTRUCTION, CLK, RESET);
        #200 RESET = 1; 
        #5 RESET = 0;
    end
        

endmodule

Lab05/part3/mycpu/cpu_wavedata.vcd
$date
	Sun May 21 17:44:24 2023
$end
$version
	Icarus Verilog
$end
$timescale
	1s
$end
$scope module cpu_tb $end
$var wire 32 ! PC [31:0] $end
$var reg 1 " CLK $end
$var reg 32 # INSTRUCTION [31:0] $end
$var reg 1 $ RESET $end
$scope module mycpu $end
$var wire 1 " CLK $end
$var wire 32 % INSTRUCTION [31:0] $end
$var wire 1 $ RESET $end
$var wire 1 & WRITEENABLE $end
$var wire 8 ' REGOUT2 [7:0] $end
$var wire 8 ( REGOUT1 [7:0] $end
$var wire 32 ) PC [31:0] $end
$var wire 8 * MUX1 [7:0] $end
$var wire 1 + IMMEDIATESELECT $end
$var wire 1 , COMPSELECT $end
$var wire 8 - COMPOUT [7:0] $end
$var wire 8 . ALURESULT [7:0] $end
$var wire 3 / ALUOP [2:0] $end
$var wire 8 0 ALUIN [7:0] $end
$scope module Alu $end
$var wire 8 1 or_result [7:0] $end
$var wire 8 2 forward_result [7:0] $end
$var wire 8 3 and_result [7:0] $end
$var wire 8 4 add_result [7:0] $end
$var wire 3 5 SELECT [0:2] $end
$var wire 8 6 RESULT [7:0] $end
$var wire 8 7 DATA2 [7:0] $end
$var wire 8 8 DATA1 [7:0] $end
$upscope $end
$scope module Control_Unit $end
$var wire 8 9 OPCODE [7:0] $end
$var reg 3 : ALUOP [2:0] $end
$var reg 1 , COMP_SELECT $end
$var reg 1 + IMMEDIATE_SELECT $end
$var reg 1 & WRITEENABLE $end
$upscope $end
$scope module Mux1 $end
$var wire 1 , SELECT $end
$var wire 8 ; DATA2 [7:0] $end
$var wire 8 < DATA1 [7:0] $end
$var reg 8 = OUTPUT [7:0] $end
$upscope $end
$scope module Mux2 $end
$var wire 8 > DATA1 [7:0] $end
$var wire 8 ? DATA2 [7:0] $end
$var wire 1 + SELECT $end
$var reg 8 @ OUTPUT [7:0] $end
$upscope $end
$scope module Pc $end
$var wire 1 " CLK $end
$var wire 1 $ RESET $end
$var wire 32 A adder_out [31:0] $end
$var reg 32 B PC [31:0] $end
$var reg 32 C PC_NEXT [31:0] $end
$upscope $end
$scope module Reg_File $end
$var wire 1 " CLK $end
$var wire 8 D IN [7:0] $end
$var wire 3 E INADDRESS [2:0] $end
$var wire 8 F OUT1 [7:0] $end
$var wire 3 G OUT1ADDRESS [2:0] $end
$var wire 8 H OUT2 [7:0] $end
$var wire 3 I OUT2ADDRESS [2:0] $end
$var wire 1 $ RESET $end
$var wire 1 & WRITE $end
$upscope $end
$scope module Two_Com $end
$var wire 8 J DATA [7:0] $end
$var wire 8 K OUT [7:0] $end
$upscope $end
$upscope $end
$upscope $end
$scope module cpu_tb $end
$scope module mycpu $end
$scope module Reg_File $end
$var reg 8 L \registers[0] [7:0] $end
$upscope $end
$upscope $end
$upscope $end
$scope module cpu_tb $end
$scope module mycpu $end
$scope module Reg_File $end
$var reg 8 M \registers[1] [7:0] $end
$upscope $end
$upscope $end
$upscope $end
$scope module cpu_tb $end
$scope module mycpu $end
$scope module Reg_File $end
$var reg 8 N \registers[2] [7:0] $end
$upscope $end
$upscope $end
$upscope $end
$scope module cpu_tb $end
$scope module mycpu $end
$scope module Reg_File $end
$var reg 8 O \registers[3] [7:0] $end
$upscope $end
$upscope $end
$upscope $end
$scope module cpu_tb $end
$scope module mycpu $end
$scope module Reg_File $end
$var reg 8 P \registers[4] [7:0] $end
$upscope $end
$upscope $end
$upscope $end
$scope module cpu_tb $end
$scope module mycpu $end
$scope module Reg_File $end
$var reg 8 Q \registers[5] [7:0] $end
$upscope $end
$upscope $end
$upscope $end
$scope module cpu_tb $end
$scope module mycpu $end
$scope module Reg_File $end
$var reg 8 R \registers[6] [7:0] $end
$upscope $end
$upscope $end
$upscope $end
$scope module cpu_tb $end
$scope module mycpu $end
$scope module Reg_File $end
$var reg 8 S \registers[7] [7:0] $end
$upscope $end
$upscope $end
$upscope $end
$enddefinitions $end
$comment Show the parameter values. $end
$dumpall
$end
#0
$dumpvars
bx S
bx R
bx Q
bx P
bx O
bx N
bx M
bx L
bx K
bx J
bx I
bx H
bx G
bx F
bx E
bx D
bx C
bx B
bx A
bx @
bx ?
bx >
bx =
bx <
bx ;
bx :
bx 9
bx 8
bx 7
bx 6
bx 5
bx 4
bx 3
bx 2
bx 1
bx 0
bx /
bx .
bx -
x,
x+
bx *
bx )
bx (
bx '
x&
bx %
1$
bx #
0"
bx !
$end
#4
1"
#5
b100 !
b100 )
b100 B
b0 S
b0 R
b0 Q
b0 P
b0 O
b0 N
b0 M
b0 L
0$
#6
b1000 C
b1000 A
#7
b101 I
b101 ?
b0 G
b0 E
b0 9
b101 #
b101 %
#8
b101 0
b101 7
b101 @
b0 /
b0 5
b0 :
1+
0,
1&
0"
#9
b101 .
b101 6
b101 D
b0 *
b0 =
b0 >
bx1x1 1
b0x0x 3
b101 2
b0 '
b0 <
b0 H
b0 J
b0 (
b0 8
b0 F
#10
b0 -
b0 ;
b0 K
b101 1
b0 3
#11
b101 4
#12
1"
#13
b101 L
b1000 !
b1000 )
b1000 B
#14
b1100 C
b1100 A
#15
b1001 0
b1001 7
b1001 @
b1 I
b1001 ?
b1 E
b10000000000001001 #
b10000000000001001 %
b101 (
b101 8
b101 F
#16
b1001 .
b1001 6
b1001 D
b1101 1
b1001 2
b1 3
0"
#17
b1110 4
#20
1"
#21
b1100 !
b1100 )
b1100 B
b1001 M
#22
b10000 C
b10000 A
#23
b1 0
b1 7
b1 @
b1 ?
b10 E
b1 9
b1001 *
b1001 =
b1001 >
b1000000100000000000000001 #
b1000000100000000000000001 %
b1001 '
b1001 <
b1001 H
b1001 J
#24
b1001 0
b1001 7
b1001 @
b1 .
b1 6
b1 D
b101 1
0+
b1 2
b11110111 -
b11110111 ;
b11110111 K
0"
#25
b1001 .
b1001 6
b1001 D
b1101 1
b1001 2
#28
1"
#29
b1001 N
b10000 !
b10000 )
b10000 B
#30
b10100 C
b10100 A
#31
b0 I
b0 ?
b10 G
b11 E
b10 9
b10000000110000001000000000 #
b10000000110000001000000000 %
#32
b1110 .
b1110 6
b1110 D
b1 /
b1 5
b1 :
0"
#33
b101 0
b101 7
b101 @
b101 *
b101 =
b101 >
b101 '
b101 <
b101 H
b101 J
b1001 (
b1001 8
b1001 F
#34
b101 2
b11111011 -
b11111011 ;
b11111011 K
#36
1"
#37
b10100 !
b10100 )
b10100 B
b1110 O
#38
b11000 C
b11000 A
#39
b1 I
b1 ?
b11 G
b100 E
b11 9
b11000001000000001100000001 #
b11000001000000001100000001 %
#40
b11111011 0
b11111011 7
b11111011 @
b11111011 *
b11111011 =
b11111011 >
1,
0"
#41
b11111011 1
b1001 3
b11111011 2
b1001 '
b1001 <
b1001 H
b1001 J
b1110 (
b1110 8
b1110 F
#42
b11110111 0
b11110111 7
b11110111 @
b11110111 *
b11110111 =
b11110111 >
b11110111 -
b11110111 ;
b11110111 K
b11111111 1
b1010 3
#43
b110 3
b11110111 2
#44
b101 .
b101 6
b101 D
b101 4
1"
#45
b101 P
b11000 !
b11000 )
b11000 B
#46
b11100 C
b11100 A
#47
b101 I
b1110101 ?
b0 G
b0 E
b0 9
b1110101 #
b1110101 %
#48
b11110111 .
b11110111 6
b11110111 D
b1110101 0
b1110101 7
b1110101 @
b1001 *
b1001 =
b1001 >
b0 /
b0 5
b0 :
1+
0,
0"
#49
b1110101 .
b1110101 6
b1110101 D
b0 *
b0 =
b0 >
b1111111 1
b100 3
b1110101 2
b0 '
b0 <
b0 H
b0 J
b101 (
b101 8
b101 F
#50
b0 -
b0 ;
b0 K
b1110101 1
b101 3
#51
b1111010 4
#52
1"
#53
b11100 !
b11100 )
b11100 B
b1110101 L
#54
b100000 C
b100000 A
#55
b10010010 0
b10010010 7
b10010010 @
b10 I
b10010010 ?
b1 E
b10000000010010010 #
b10000000010010010 %
b1110101 (
b1110101 8
b1110101 F
#56
b10010010 .
b10010010 6
b10010010 D
b11110111 1
b10010010 2
b10000 3
0"
#57
b1001 *
b1001 =
b1001 >
b1001 '
b1001 <
b1001 H
b1001 J
b111 4
#58
b11110111 -
b11110111 ;
b11110111 K
#60
1"
#61
b10010010 M
b100000 !
b100000 )
b100000 B
#62
b100100 C
b100100 A
#63
b0 0
b0 7
b0 @
b0 I
b0 ?
b1 G
b101 E
b100 9
b100000001010000000100000000 #
b100000001010000000100000000 %
#64
b0 .
b0 6
b0 D
b1001 0
b1001 7
b1001 @
b1110101 1
b0 3
b0 2
b10 /
b10 5
b10 :
0+
0"
#65
b1110101 0
b1110101 7
b1110101 @
b1 .
b1 6
b1 D
b1110101 *
b1110101 =
b1110101 >
b1111101 1
b1 3
b1001 2
b1110101 '
b1110101 <
b1110101 H
b1110101 J
b10010010 (
b10010010 8
b10010010 F
#66
b10000 .
b10000 6
b10000 D
b1110101 2
b10001011 -
b10001011 ;
b10001011 K
b11110111 1
b10000 3
#68
1"
#69
b100100 !
b100100 )
b100100 B
b10000 Q
#70
b101000 C
b101000 A
#71
b10 I
b10 ?
b101 G
b110 E
b101 9
b101000001100000010100000010 #
b101000001100000010100000010 %
#72
b11110111 .
b11110111 6
b11110111 D
b11 /
b11 5
b11 :
0"
#73
b1001 0
b1001 7
b1001 @
b1001 *
b1001 =
b1001 >
b1001 '
b1001 <
b1001 H
b1001 J
b10000 (
b10000 8
b10000 F
#74
b11001 .
b11001 6
b11001 D
b0 3
b1001 2
b11110111 -
b11110111 ;
b11110111 K
b11001 1
#75
b11001 4
#76
1"
#77
b11001 R
b101000 !
b101000 )
b101000 B
#78
b101100 C
b101100 A
#79
bx I
bx ?
bx G
bx E
bx 9
bx #
bx %
#80
0"
#81
bx 0
bx 7
bx @
bx *
bx =
bx >
bx '
bx <
bx H
bx J
bx (
bx 8
bx F
#82
bx .
bx 6
bx D
bx 2
bx -
bx ;
bx K
bx 1
bx 3
#83
bx 4
#84
1"
#85
b101100 !
b101100 )
b101100 B
#86
b110000 C
b110000 A
#88
0"
#92
1"
#93
b110000 !
b110000 )
b110000 B
#94
b110100 C
b110100 A
#96
0"
#100
1"
#101
b110100 !
b110100 )
b110100 B
#102
b111000 C
b111000 A
