Lab05/part3/alu.v
// CO224 - Lab05 PART-1
// GROUP - 11

// ALU module 
// 8-bit ALU unit, that can operate with two 8-bit numbers to generate the result
// give the relevant output to RESULT respect to SELECT 

// Input:
//      DATA1, DATA2, SELECT
// Output:
//      RESULT

// Operations:
//      FORWARD - forward the data in DATA2 into RESULT 
//      ADD     - add DATA1 and DATA2, give the addiction to RESULT
//      AND     - and DATA1 and DATA2, give the result to RESULT     
//      OR      - or DATA1 and DATA2, give the result to RESULT  

// SELECTION CODE:
//      FOEWARD - 000   
//      ADD     - 001
//      AND     - 010   
//      OR      - 011

module alu(DATA1, DATA2, RESULT, SELECT);

    // initailize input ports
    input [7:0] DATA1, DATA2;
    input [0:2] SELECT;
    // initailize output ports
    output [7:0] RESULT;

    // make wires for connect each module's outputs to the mux
    wire [7:0] forward_result, add_result, and_result, or_result;

    // make instances of for each module
    // FORWARD - alu_forward
    // ADD     - alu_add
    // AND     - alu_and
    // OR      - alu_or
    // connect each module's relevant input and output
    ALU_FORWARD alu_forward(DATA2, forward_result);
    ALU_ADD alu_add(DATA1, DATA2, add_result);
    ALU_AND alu_and(DATA1, DATA2, and_result);
    ALU_OR alu_or(DATA1, DATA2, or_result);

    // instantiation of the mux
    // connect all the the module's output to the mux 
    // select a input as the selection
    MUX mux(forward_result, add_result, and_result, or_result, RESULT, SELECT);

endmodule


// FORWARD module
// used to foward the 8 bit DATA2 directly to output of the module
// Inputs  - DATA2
// Outputs - RESULT
module ALU_FORWARD(DATA2, RESULT);

    // initailize input ports
    input [7:0] DATA2;
    // initailize output ports
    output [7:0] RESULT;

    // assigen the DATA2 value to RESULT with a 1 time unit delay
    assign #1 RESULT = DATA2;

endmodule


// ADD module
// 8 bit adder for add two 8 bit number and give a 8 bit result
// Inputs - DATA1, DATA2
// Output - RESULT
module ALU_ADD(DATA1, DATA2, RESULT);

    // initailize input ports
    input [7:0] DATA1, DATA2;
    // initailize output ports
    output [7:0] RESULT;

    // get the addition of DATA1 and DATA2 
    // assign the value to RESULT with a 2 time units delay
    assign #2 RESULT = DATA1 + DATA2;

endmodule


// AND module
// bitwise AND the give two 8 bit numbers and output a 8 bit number
// Inout  - DATA1, DATA2
// Output - RESULT
module ALU_AND(DATA1, DATA2, RESULT);

    // initailize input ports
    input [7:0] DATA1, DATA2;
    // initailize output ports
    output [7:0] RESULT;

    // AND bitwise each bit
    // assign it to RESULT with a 1 time unit delay
    assign #1 RESULT = DATA1 & DATA2;

endmodule


// OR module
// bitwise OR the give two 8 bit numbers and output a 8 bit number
// Inout  - DATA1, DATA2
// Output - RESULT
module ALU_OR(DATA1, DATA2, RESULT);

    // initailize input ports
    input [7:0] DATA1, DATA2;
    // initailize output ports
    output [7:0] RESULT;

    // and bitwise each bit
    // assign it to RESULT with a 1 time unit delay
    assign #1 RESULT = DATA1 | DATA2;

endmodule


// MUX module
// select a inputs for the inputs
// map it to the ouput reference to the selection bits
// Inputs  - forward_result, add_result, and_result, or_result, SELECT
// Outputs - RESULT
module MUX(forward_result, add_result, and_result, or_result, RESULT, SELECT);

    // initailize input ports
    input [7:0] forward_result, add_result, and_result, or_result;
    input [2:0] SELECT;
    // initailize output ports
    output [7:0] RESULT;
    // initailize the registers
    reg [7:0] RESULT;

    // set a always block to trigger when changing 
    // forward_result, add_result, and_result, or_result, SELECT
    // thus, if these inputs are change the output is change reference to selection bits
    always @(forward_result, add_result, and_result, or_result, SELECT) begin
        
        // case block to check the select bit
        // give the result value 
        case(SELECT)

            // selection for FORWARD
            3'b000 : RESULT = forward_result;
            // selection for ADD
            3'b001 : RESULT = add_result;
            // selection for AND
            3'b010 : RESULT = and_result;
            // selection for OR
            3'b011 : RESULT = or_result;

            // deafult routing
            default : RESULT = 0;
        endcase

    end

endmodule

Lab05/part3/mycpu/modules.v
module two_comp(DATA, OUT);

    input [7:0] DATA;
    output [7:0] OUT;

    assign #1 OUT = ~DATA + 1;

endmodule


module mux(DATA1, DATA2, SELECT, OUTPUT);

    input [7:0] DATA1, DATA2;
    input SELECT;
    output reg [7:0] OUTPUT;

    always @(DATA1, DATA2, SELECT) begin 

        if (SELECT) 
            OUTPUT = DATA2;
        else
            OUTPUT = DATA1;

    end

    always @(DATA1, DATA2, SELECT, OUTPUT)
    $display($time, " >> %d %d %d %d", DATA1, DATA2, SELECT, OUTPUT);
    

endmodule

Lab05/part3/mycpu/reg_file.v
// CO224 - Lab05 PART-1
// GROUP - 11

// REGISTER FILE module
// 8x8 register file that can store 8-bit binary numbers
// register numbers are 0-7
// INPUT ports: 
//     INADDRESS, OUT1ADDRESS, OUT2ADDRESS : 3-bit
//     IN : 8-bit
//     WRITE, CLK, RESET : 1-bit
// OUTPUT ports:
//     OUT1, OUT2 : 8-bit
// Reading  - for given register numbers(OUT1ADDRESS, OUT2ADDRESS), 
//            OUT1 and OUT2 will output the stored value asynchronously
//            reading delay - 2 time unit
// Writting - to a given register numbers(INADDRESS),
//            IN data will write synchronously when a positive clk edge and WRITE is enable
//            writting delay - 1 time unit
// Reset    - when reset is enable, all the register values will reset to 0 in a positive clk edge
module reg_file(IN, OUT1, OUT2, INADDRESS, OUT1ADDRESS, OUT2ADDRESS, WRITE, CLK, RESET);

    // declare input ports
    input [7:0] IN; // data in
    input [2:0]  INADDRESS, OUT1ADDRESS, OUT2ADDRESS;   // register numbers 
    input  WRITE, CLK, RESET;   // control signals

    // declare output ports
    output [7:0] OUT1, OUT2;    // data out
    
    // declare the 8-bit, 8 registers
    reg [7:0] registers [7:0];

    // assign block for change the OUT1, in a change of OUT1ADDRESS or register values
    // with a 2 time unit delay
    assign #2 OUT1 = registers[OUT1ADDRESS];

    // assign block for chnage the OUT1, in a change of OUT2ADDRESS or register values
    // with a 2 time unit delay
    assign #2 OUT2 = registers[OUT2ADDRESS];

    // always block for check for a positive clk edge
    // to write a reg or reset registers
    always @(posedge CLK) begin
        
        // to write a register
        // WRITE should be enable and RESET should be desable
        if (WRITE && ~RESET) begin
            
            // select the appropriate reg numbers
            // writting takes 1 time unit time
            #1 registers[INADDRESS] = IN;

        end

        // if RESET is enable
        // set all the register values to 0
        if (RESET) begin        
            
            #1 // one time unit delay for resetting
            // loop through all the registers
            for (integer i=0; i<8; i=i+1) begin
                registers[i] = 0;   // assign 0 to the registers
            end

        end

    end

    always @(IN, OUT1, OUT2, INADDRESS, OUT1ADDRESS, OUT2ADDRESS, WRITE, CLK, RESET, registers[0], registers[1], registers[2], registers[3], registers[4], registers[5], registers[6], registers[7])
    $display($time, " %d %d %d %d %d %d %d %d %d %d %d %d %d %d %d %d %d",IN, OUT1, OUT2, INADDRESS, OUT1ADDRESS, OUT2ADDRESS, WRITE, CLK, RESET, registers[0], registers[1], registers[2], registers[3], registers[4], registers[5], registers[6], registers[7]);

endmodule

Lab05/part3/mycpu/control_unit.v
// CO224 - Lab05 PART-3
// GROUP - 11

// Control Unit
// To decode the OpCode and make the control signals

module control_unit(OPCODE, WRITEENABLE, COMP_SELECT, IMMEDIATE_SELECT, ALUOP);

    // declaration of input output retisters
    input [7:0] OPCODE; 
    output reg WRITEENABLE, COMP_SELECT, IMMEDIATE_SELECT; //control signal
    output reg [2:0] ALUOP; // control signal for ALU (2 bit signal)

    // alway block for Opcodes
    always @(OPCODE) begin 

        // delay of the dedcoding
        #1
        //enabling the control signals according to the OPCODE
        case (OPCODE)
            // loadi - load the register with the given immediate value 
            8'b0000_0000: begin
                WRITEENABLE = 1'b1; // control signal to write to the register
                COMP_SELECT = 1'b0; 
                IMMEDIATE_SELECT = 1'b1; // immediate number select
                ALUOP = 3'b000; // select forward result from ALU
            end

            //mov - copy a value in a register to another register
            8'b0000_0001: begin
                WRITEENABLE = 1'b1;
                COMP_SELECT = 1'b0;
                IMMEDIATE_SELECT = 1'b0;
                ALUOP = 3'b000;
            end

            // add - add 2 register values and write the result to another register
            8'b0000_0010: begin
                WRITEENABLE = 1'b1;
                COMP_SELECT = 1'b0;
                IMMEDIATE_SELECT = 1'b0;
                ALUOP = 3'b001; //select add result from alu
            end

            // sub - subtract 2 reg values and write the result to another register
            8'b0000_0011: begin
                WRITEENABLE = 1'b1;
                COMP_SELECT = 1'b1; // 2s complement enables(input for aku module is 2's complemented)
                IMMEDIATE_SELECT = 1'b0;
                ALUOP = 3'b001; // select add from ALU
            end

            // and - bitwise AND of 2 reg values
            8'b0000_0100: begin
                WRITEENABLE = 1'b1;
                COMP_SELECT = 1'b0;
                IMMEDIATE_SELECT = 1'b0;
                ALUOP = 3'b010; // select and result form alu
            end

            // or - bitwise OR of 2 reg values
            8'b0000_0101: begin
                WRITEENABLE = 1'b1;
                COMP_SELECT = 1'b0;
                IMMEDIATE_SELECT = 1'b0;
                ALUOP = 3'b011; // select or result from ALU
            end

        endcase

    end

endmodule

Lab05/part3/mycpu/pc.v
module pc(RESET, CLK, PC);

    input RESET, CLK;
    output reg [31:0] PC;
    
    reg [31:0] PC_NEXT;
    wire [31:0] adder_out;

    pc_add pc_adder(PC, adder_out);

    initial
    #1 PC = 0;

    always @(adder_out)
    PC_NEXT = adder_out;

    always @(posedge CLK) begin

        if (RESET)
            #1 PC = 32'b00000000000000000000000000000100;
        else
            #1 PC = PC_NEXT;

    end 

endmodule

module pc_add(PC, adder_out);

    input [31:0] PC;
    output [31:0] adder_out;

    assign #1 adder_out = PC + 4 ;

endmodule

Lab05/part3/mycpu/cpu.v
`include "alu.v"
`include "reg_file.v"
`include "pc.v"
`include "control_unit.v"
`include "modules.v"


module cpu(PC, INSTRUCTION, CLK, RESET);

    input CLK, RESET;
    input [31:0] INSTRUCTION;

    output [31:0] PC;

    wire [2:0] ALUOP;
    wire WRITEENABLE, COMPSELECT, IMMEDIATESELECT;
    wire [7:0] ALURESULT, REGOUT2, REGOUT1, COMPOUT, MUX1, ALUIN;


    pc Pc(RESET, CLK, PC);
    control_unit Control_Unit(INSTRUCTION[31:24], WRITEENABLE, COMPSELECT, IMMEDIATESELECT, ALUOP);
    reg_file Reg_File(ALURESULT, REGOUT1, REGOUT2, INSTRUCTION[18:16], INSTRUCTION[10:8], INSTRUCTION[2:0], WRITEENABLE, CLK,RESET);
    two_comp Two_Comp(REGOUT2, COMPOUT);

    mux Mux1(REGOUT2, COMPOUT, COMPSELECT, MUX1);
    mux Mux2(MUX1, INSTRUCTION[7:0], IMMEDIATESELECT, ALUIN);

    alu Alu(REGOUT1, ALUIN, ALURESULT, ALUOP);

    always @(INSTRUCTION, ALUIN, IMMEDIATESELECT)
    $display($time, " %d %d %d", INSTRUCTION[7:0], ALUIN, IMMEDIATESELECT);
    

endmodule

Lab05/part3/mycpu/cpu_tb.v
// Computer Architecture (CO224) - Lab 05
// Design: Testbench of Integrated CPU of Simple Processor
// Author: Isuru Nawinne

`include "cpu.v"

module cpu_tb;

    reg CLK, RESET;
    wire [31:0] PC;
    // wire [31:0] INSTRUCTION;
    reg [31:0] INSTRUCTION;
    
    /* 
    ------------------------
     SIMPLE INSTRUCTION MEM
    ------------------------
    */
    
    // TODO: Initialize an array of registers (8x1024) named 'instr_mem' to be used as instruction memory
    reg [7:0] instr_mem [1023:0];

    
    
    // TODO: Create combinational logic to support CPU instruction fetching, given the Program Counter(PC) value 
    //       (make sure you include the delay for instruction fetching here)

    always @(PC) begin
        #2
        INSTRUCTION[31:24] = instr_mem[PC-1];
        INSTRUCTION[23:16] = instr_mem[PC-2];
        INSTRUCTION[15:8] = instr_mem[PC-3];
        INSTRUCTION[7:0] = instr_mem[PC-4];

    end
    
    initial
    begin
        // Initialize instruction memory with the set of instructions you need execute on CPU
        
        // METHOD 1: manually loading instructions to instr_mem
        // {instr_mem[10'd3], instr_mem[10'd2], instr_mem[10'd1], instr_mem[10'd0]} = 32'b00000000000001000000000000000101;
        // {instr_mem[10'd7], instr_mem[10'd6], instr_mem[10'd5], instr_mem[10'd4]} = 32'b00000000000000100000000000001001;
        // {instr_mem[10'd11], instr_mem[10'd10], instr_mem[10'd9], instr_mem[10'd8]} = 32'b00000010000001100000010000000010;
        
        // METHOD 2: loading instr_mem content from instr_mem.mem file
        $readmemb("instr_mem.mem", instr_mem);
    end
    
    /* 
    -----
     CPU
    -----
    */
    cpu mycpu(PC, INSTRUCTION, CLK, RESET);

    initial
    begin
    
        // generate files needed to plot the waveform using GTKWave
        $dumpfile("cpu_wavedata.vcd");
		$dumpvars(0, cpu_tb);
        
        CLK = 1'b0;
        RESET = 1'b0;
        
        // TODO: Reset the CPU (by giving a pulse to RESET signal) to start the program execution
        
        // finish simulation after some time
        #100
        $finish;
        
    end
    
    // clock signal generation
    always
    #4 CLK = ~CLK;

    initial begin
        $monitor($time, " %b %b %b %b", PC, INSTRUCTION, CLK, RESET);
        #200 RESET = 1; 
        #5 RESET = 0;
    end
        

endmodule

Lab05/part3/mycpu/cpu_wavedata.vcd
$date
	Fri May 12 08:44:35 2023
$end
$version
	Icarus Verilog
$end
$timescale
	1s
$end
$scope module cpu_tb $end
$var wire 32 ! PC [31:0] $end
$var reg 1 " CLK $end
$var reg 32 # INSTRUCTION [31:0] $end
$var reg 1 $ RESET $end
$scope module mycpu $end
$var wire 1 " CLK $end
$var wire 32 % INSTRUCTION [31:0] $end
$var wire 1 $ RESET $end
$var wire 1 & WRITEENABLE $end
$var wire 8 ' REGOUT2 [7:0] $end
$var wire 8 ( REGOUT1 [7:0] $end
$var wire 32 ) PC [31:0] $end
$var wire 8 * MUX1 [7:0] $end
$var wire 1 + IMMEDIATESELECT $end
$var wire 1 , COMPSELECT $end
$var wire 8 - COMPOUT [7:0] $end
$var wire 8 . ALURESULT [7:0] $end
$var wire 3 / ALUOP [2:0] $end
$var wire 8 0 ALUIN [7:0] $end
$scope module Alu $end
$var wire 8 1 or_result [7:0] $end
$var wire 8 2 forward_result [7:0] $end
$var wire 8 3 and_result [7:0] $end
$var wire 8 4 add_result [7:0] $end
$var wire 3 5 SELECT [0:2] $end
$var wire 8 6 RESULT [7:0] $end
$var wire 8 7 DATA2 [7:0] $end
$var wire 8 8 DATA1 [7:0] $end
$scope module alu_add $end
$var wire 8 9 RESULT [7:0] $end
$var wire 8 : DATA2 [7:0] $end
$var wire 8 ; DATA1 [7:0] $end
$upscope $end
$scope module alu_and $end
$var wire 8 < RESULT [7:0] $end
$var wire 8 = DATA2 [7:0] $end
$var wire 8 > DATA1 [7:0] $end
$upscope $end
$scope module alu_forward $end
$var wire 8 ? RESULT [7:0] $end
$var wire 8 @ DATA2 [7:0] $end
$upscope $end
$scope module alu_or $end
$var wire 8 A RESULT [7:0] $end
$var wire 8 B DATA2 [7:0] $end
$var wire 8 C DATA1 [7:0] $end
$upscope $end
$scope module mux $end
$var wire 8 D add_result [7:0] $end
$var wire 8 E and_result [7:0] $end
$var wire 8 F forward_result [7:0] $end
$var wire 8 G or_result [7:0] $end
$var wire 3 H SELECT [2:0] $end
$var reg 8 I RESULT [7:0] $end
$upscope $end
$upscope $end
$scope module Control_Unit $end
$var wire 8 J OPCODE [7:0] $end
$var reg 3 K ALUOP [2:0] $end
$var reg 1 , COMP_SELECT $end
$var reg 1 + IMMEDIATE_SELECT $end
$var reg 1 & WRITEENABLE $end
$upscope $end
$scope module Mux1 $end
$var wire 1 , SELECT $end
$var wire 8 L DATA2 [7:0] $end
$var wire 8 M DATA1 [7:0] $end
$var reg 8 N OUTPUT [7:0] $end
$upscope $end
$scope module Mux2 $end
$var wire 8 O DATA1 [7:0] $end
$var wire 8 P DATA2 [7:0] $end
$var wire 1 + SELECT $end
$var reg 8 Q OUTPUT [7:0] $end
$upscope $end
$scope module Pc $end
$var wire 1 " CLK $end
$var wire 1 $ RESET $end
$var wire 32 R adder_out [31:0] $end
$var reg 32 S PC [31:0] $end
$var reg 32 T PC_NEXT [31:0] $end
$scope module pc_adder $end
$var wire 32 U PC [31:0] $end
$var wire 32 V adder_out [31:0] $end
$upscope $end
$upscope $end
$scope module Reg_File $end
$var wire 1 " CLK $end
$var wire 8 W IN [7:0] $end
$var wire 3 X INADDRESS [2:0] $end
$var wire 8 Y OUT1 [7:0] $end
$var wire 3 Z OUT1ADDRESS [2:0] $end
$var wire 8 [ OUT2 [7:0] $end
$var wire 3 \ OUT2ADDRESS [2:0] $end
$var wire 1 $ RESET $end
$var wire 1 & WRITE $end
$scope begin $ivl_for_loop0 $end
$var integer 32 ] i [31:0] $end
$upscope $end
$upscope $end
$scope module Two_Comp $end
$var wire 8 ^ DATA [7:0] $end
$var wire 8 _ OUT [7:0] $end
$upscope $end
$upscope $end
$upscope $end
$enddefinitions $end
$comment Show the parameter values. $end
$dumpall
$end
#0
$dumpvars
bx _
bx ^
bx ]
bx \
bx [
bx Z
bx Y
bx X
bx W
bx V
bx U
bx T
bx S
bx R
bx Q
bx P
bx O
bx N
bx M
bx L
bx K
bx J
bx I
bx H
bx G
bx F
bx E
bx D
bx C
bx B
bx A
bx @
bx ?
bx >
bx =
bx <
bx ;
bx :
bx 9
bx 8
bx 7
bx 6
bx 5
bx 4
bx 3
bx 2
bx 1
bx 0
bx /
bx .
bx -
x,
x+
bx *
bx )
bx (
bx '
x&
bx %
0$
bx #
0"
bx !
$end
#1
b0 !
b0 )
b0 S
b0 U
#2
b100 T
b100 R
b100 V
#4
1"
#5
b100 !
b100 )
b100 S
b100 U
#6
b1000 T
b1000 R
b1000 V
#7
b101 \
b101 P
b0 Z
b100 X
b0 J
b1000000000000000101 #
b1000000000000000101 %
#8
b101 0
b101 7
b101 :
b101 =
b101 @
b101 B
b101 Q
b0 /
b0 5
b0 H
b0 K
1+
0,
1&
0"
#9
b101 .
b101 6
b101 I
b101 W
bx1x1 1
bx1x1 A
bx1x1 G
b0x0x 3
b0x0x <
b0x0x E
b101 2
b101 ?
b101 F
#12
1"
#13
b1000 !
b1000 )
b1000 S
b1000 U
#14
b1100 T
b1100 R
b1100 V
#15
b1001 0
b1001 7
b1001 :
b1001 =
b1001 @
b1001 B
b1001 Q
b1 \
b1001 P
b10 X
b100000000000001001 #
b100000000000001001 %
#16
b1001 .
b1001 6
b1001 I
b1001 W
bx1xx1 1
bx1xx1 A
bx1xx1 G
b0x00x 3
b0x00x <
b0x00x E
b1001 2
b1001 ?
b1001 F
0"
#20
1"
#21
b1100 !
b1100 )
b1100 S
b1100 U
#22
b10000 T
b10000 R
b10000 V
#23
b10 0
b10 7
b10 :
b10 =
b10 @
b10 B
b10 Q
b10 \
b10 P
b100 Z
b110 X
b10 J
b10000001100000010000000010 #
b10000001100000010000000010 %
#24
bx .
bx 6
bx I
bx W
bx 0
bx 7
bx :
bx =
bx @
bx B
bx Q
bx1x 1
bx1x A
bx1x G
b0x0 3
b0x0 <
b0x0 E
b10 2
b10 ?
b10 F
b1 /
b1 5
b1 H
b1 K
0+
0"
#25
b1001 0
b1001 7
b1001 :
b1001 =
b1001 @
b1001 B
b1001 Q
b1001 *
b1001 N
b1001 O
bx 1
bx A
bx G
bx 3
bx <
bx E
bx 2
bx ?
bx F
b1001 '
b1001 M
b1001 [
b1001 ^
b101 (
b101 8
b101 ;
b101 >
b101 C
b101 Y
#26
b1001 2
b1001 ?
b1001 F
b11110111 -
b11110111 L
b11110111 _
b1101 1
b1101 A
b1101 G
b1 3
b1 <
b1 E
#27
b1110 .
b1110 6
b1110 I
b1110 W
b1110 4
b1110 9
b1110 D
#28
1"
#29
b10000 !
b10000 )
b10000 S
b10000 U
#30
b10100 T
b10100 R
b10100 V
#31
b110 \
b110 P
b0 Z
b0 X
b1 J
b1000000000000000000000110 #
b1000000000000000000000110 %
#32
b1001 .
b1001 6
b1001 I
b1001 W
b0 /
b0 5
b0 H
b0 K
0"
#33
b1110 0
b1110 7
b1110 :
b1110 =
b1110 @
b1110 B
b1110 Q
b1110 *
b1110 N
b1110 O
b1110 '
b1110 M
b1110 [
b1110 ^
bx (
bx 8
bx ;
bx >
bx C
bx Y
#34
b1110 .
b1110 6
b1110 I
b1110 W
b1110 2
b1110 ?
b1110 F
b11110010 -
b11110010 L
b11110010 _
bx111x 1
bx111x A
bx111x G
b0xxx0 3
b0xxx0 <
b0xxx0 E
#35
bx 4
bx 9
bx D
#36
1"
#37
b10100 !
b10100 )
b10100 S
b10100 U
#38
b11000 T
b11000 R
b11000 V
#39
b1 \
b1 P
b1 X
b0 J
b10000000000000001 #
b10000000000000001 %
b1110 (
b1110 8
b1110 ;
b1110 >
b1110 C
b1110 Y
#40
b1 0
b1 7
b1 :
b1 =
b1 @
b1 B
b1 Q
1+
b1110 1
b1110 A
b1110 G
b1110 3
b1110 <
b1110 E
0"
#41
b1 .
b1 6
b1 I
b1 W
bx *
bx N
bx O
b1111 1
b1111 A
b1111 G
b0 3
b0 <
b0 E
b1 2
b1 ?
b1 F
bx '
bx M
bx [
bx ^
#42
bx -
bx L
bx _
b1111 4
b1111 9
b1111 D
#44
1"
#45
b11000 !
b11000 )
b11000 S
b11000 U
#46
b11100 T
b11100 R
b11100 V
#47
b10 Z
b10 X
b10 J
b1 *
b1 N
b1 O
b10000000100000001000000001 #
b10000000100000001000000001 %
b1 '
b1 M
b1 [
b1 ^
#48
b1111 .
b1111 6
b1111 I
b1111 W
b1 /
b1 5
b1 H
b1 K
0+
b11111111 -
b11111111 L
b11111111 _
0"
#49
b1001 (
b1001 8
b1001 ;
b1001 >
b1001 C
b1001 Y
#50
b1001 1
b1001 A
b1001 G
b1 3
b1 <
b1 E
#51
b1010 .
b1010 6
b1010 I
b1010 W
b1010 4
b1010 9
b1010 D
#52
1"
#53
b11100 !
b11100 )
b11100 S
b11100 U
#54
b100000 T
b100000 R
b100000 V
#55
bx \
bx P
bx Z
bx X
bx J
bx #
bx %
b1010 (
b1010 8
b1010 ;
b1010 >
b1010 C
b1010 Y
#56
b1011 1
b1011 A
b1011 G
b0 3
b0 <
b0 E
0"
#57
bx 0
bx 7
bx :
bx =
bx @
bx B
bx Q
bx *
bx N
bx O
b1011 .
b1011 6
b1011 I
b1011 W
bx '
bx M
bx [
bx ^
bx (
bx 8
bx ;
bx >
bx C
bx Y
b1011 4
b1011 9
b1011 D
#58
bx 2
bx ?
bx F
bx -
bx L
bx _
bx 1
bx A
bx G
bx 3
bx <
bx E
#59
bx .
bx 6
bx I
bx W
bx 4
bx 9
bx D
#60
1"
#61
b100000 !
b100000 )
b100000 S
b100000 U
#62
b100100 T
b100100 R
b100100 V
#64
0"
#68
1"
#69
b100100 !
b100100 )
b100100 S
b100100 U
#70
b101000 T
b101000 R
b101000 V
#72
0"
#76
1"
#77
b101000 !
b101000 )
b101000 S
b101000 U
#78
b101100 T
b101100 R
b101100 V
#80
0"
#84
1"
#85
b101100 !
b101100 )
b101100 S
b101100 U
#86
b110000 T
b110000 R
b110000 V
#88
0"
#92
1"
#93
b110000 !
b110000 )
b110000 S
b110000 U
#94
b110100 T
b110100 R
b110100 V
