Lab05/part2/reg_file.v
// CO224 - Lab05 PART-1
// GROUP - 11

// REGISTER FILE module
// 8x8 register file that can store 8-bit binary numbers
// register numbers are 0-7
// INPUT ports: 
//     INADDRESS, OUT1ADDRESS, OUT2ADDRESS : 3-bit
//     IN : 8-bit
//     WRITE, CLK, RESET : 1-bit
// OUTPUT ports:
//     OUT1, OUT2 : 8-bit
// Reading  - for given register numbers(OUT1ADDRESS, OUT2ADDRESS), 
//            OUT1 and OUT2 will output the stored value asynchronously
//            reading delay - 2 time unit
// Writting - to a given register numbers(INADDRESS),
//            IN data will write synchronously when a positive clk edge and WRITE is enable
//            writting delay - 1 time unit
// Reset    - when reset is enable, all the register values will reset to 0 in a positive clk edge
module reg_file(IN, OUT1, OUT2, INADDRESS, OUT1ADDRESS, OUT2ADDRESS, WRITE, CLK, RESET);

    // declare input ports
    input [7:0] IN; // data in
    input [2:0]  INADDRESS, OUT1ADDRESS, OUT2ADDRESS;   // register numbers 
    input  WRITE, CLK, RESET;   // control signals

    // declare output ports
    output [7:0] OUT1, OUT2;    // data out
    
    // declare the 8-bit, 8 registers
    reg [7:0] registers [7:0];

    // assign block for change the OUT1, in a change of OUT1ADDRESS or register values
    // with a 2 time unit delay
    assign #2 OUT1 = registers[OUT1ADDRESS];

    // assign block for chnage the OUT1, in a change of OUT2ADDRESS or register values
    // with a 2 time unit delay
    assign #2 OUT2 = registers[OUT2ADDRESS];

    // always block for check for a positive clk edge
    // to write a reg or reset registers
    always @(posedge CLK) begin
        
        // to write a register
        // WRITE should be enable and RESET should be desable
        if (WRITE && ~RESET) begin
            
            // select the appropriate reg numbers
            // writting takes 1 time unit time
            #1 registers[INADDRESS] = IN;

        end

        // if RESET is enable
        // set all the register values to 0
        if (RESET) begin
            registers[0] = 0; // 0 to register0
            registers[1] = 0; // 0 to register1
            registers[2] = 0; // 0 to register2
            registers[3] = 0; // 0 to register3
            registers[4] = 0; // 0 to register4
            registers[5] = 0; // 0 to register5
            registers[6] = 0; // 0 to register6
            registers[7] = 0; // 0 to register7
        end

    end

endmodule

Lab05/part2/reg_file_tb.v
// Computer Architecture (CO224) - Lab 05
// Design: Register File of Simple Processor

`include "reg_file.v"

module reg_file_tb;
    
    reg [7:0] WRITEDATA;
    reg [2:0] WRITEREG, READREG1, READREG2;
    reg CLK, RESET, WRITEENABLE; 
    wire [7:0] REGOUT1, REGOUT2;
    
    reg_file regfile(WRITEDATA, REGOUT1, REGOUT2, WRITEREG, READREG1, READREG2, WRITEENABLE, CLK, RESET);

    initial
    $monitor($time, "WRITEDATA = %d | REGOUT1 = %d, REGOUT2 = %d | WRITEREG =  %d, READREG1 = %d, READREG2 = %d | WRITEENABLE = %d, CLK = %d, RESET %d",WRITEDATA, REGOUT1, REGOUT2, WRITEREG, READREG1, READREG2, WRITEENABLE, CLK, RESET);
       
    initial
    begin
        CLK = 1'b1;
        
        // generate files needed to plot the waveform using GTKWave
        $dumpfile("reg_file_wavedata.vcd");
		$dumpvars(0, reg_file_tb);
        
        // assign values with time to input signals to see output 
        RESET = 1'b0;
        WRITEENABLE = 1'b0;
        
        #4
        RESET = 1'b1;
        READREG1 = 3'd0;
        READREG2 = 3'd4;
        
        #6
        RESET = 1'b0;
        
        #2
        WRITEREG = 3'd2;
        WRITEDATA = 8'd95;
        WRITEENABLE = 1'b1;
        
        #7
        WRITEENABLE = 1'b0;
        
        #1
        READREG1 = 3'd2;
        
        #7
        WRITEREG = 3'd1;
        WRITEDATA = 8'd28;
        WRITEENABLE = 1'b1;
        READREG1 = 3'd1;
        
        #8
        WRITEENABLE = 1'b0;
        
        #8
        WRITEREG = 3'd4;
        WRITEDATA = 8'd6;
        WRITEENABLE = 1'b1;
        
        #8
        WRITEDATA = 8'd15;
        WRITEENABLE = 1'b1;
        
        #10
        WRITEENABLE = 1'b0;
        
        #6
        WRITEREG = -3'd1;
        WRITEDATA = 8'd50;
        WRITEENABLE = 1'b1;
        
        #5
        WRITEENABLE = 1'b0;
        
        #10
        $finish;
    end
    
    // clock signal generation
    always
        #4 CLK = ~CLK;
        

endmodule

Lab05/part2/reg_file_wavedata.vcd
$date
	Tue May 09 22:11:20 2023
$end
$version
	Icarus Verilog
$end
$timescale
	1s
$end
$scope module reg_file_tb $end
$var wire 8 ! REGOUT2 [7:0] $end
$var wire 8 " REGOUT1 [7:0] $end
$var reg 1 # CLK $end
$var reg 3 $ READREG1 [2:0] $end
$var reg 3 % READREG2 [2:0] $end
$var reg 1 & RESET $end
$var reg 8 ' WRITEDATA [7:0] $end
$var reg 1 ( WRITEENABLE $end
$var reg 3 ) WRITEREG [2:0] $end
$scope module regfile $end
$var wire 1 # CLK $end
$var wire 8 * IN [7:0] $end
$var wire 3 + INADDRESS [2:0] $end
$var wire 8 , OUT1 [7:0] $end
$var wire 3 - OUT1ADDRESS [2:0] $end
$var wire 8 . OUT2 [7:0] $end
$var wire 3 / OUT2ADDRESS [2:0] $end
$var wire 1 & RESET $end
$var wire 1 ( WRITE $end
$upscope $end
$upscope $end
$enddefinitions $end
$comment Show the parameter values. $end
$dumpall
$end
#0
$dumpvars
bx /
bx .
bx -
bx ,
bx +
bx *
bx )
0(
bx '
0&
bx %
bx $
1#
bx "
bx !
$end
#4
0#
b100 %
b100 /
b0 $
b0 -
1&
#8
1#
#10
b0 !
b0 .
b0 "
b0 ,
0&
#12
1(
b1011111 '
b1011111 *
b10 )
b10 +
0#
#16
1#
#19
0(
#20
b10 $
b10 -
0#
#22
b1011111 "
b1011111 ,
#24
1#
#27
b1 $
b1 -
1(
b11100 '
b11100 *
b1 )
b1 +
#28
0#
#29
b0 "
b0 ,
#32
1#
#35
b11100 "
b11100 ,
0(
#36
0#
#40
1#
#43
1(
b110 '
b110 *
b100 )
b100 +
#44
0#
#48
1#
#51
b110 !
b110 .
b1111 '
b1111 *
#52
0#
#56
1#
#59
b1111 !
b1111 .
#60
0#
#61
0(
#64
1#
#67
1(
b110010 '
b110010 *
b111 )
b111 +
#68
0#
#72
1#
0(
